[{"id": 0, "type": "单选题", "question": "国网大数据应用业务体系是？", "options": ["两支撑两赋能", "两支撑三赋能", "三支撑两赋能", "三支撑三赋能"], "answer": "B", "analysis": "", "sheet": "单选题"}, {"id": 1, "type": "单选题", "question": "当前大数据技术的基础是由（ ）首先提出的", "options": ["微软", "百度", "谷歌", "阿里巴巴"], "answer": "C", "analysis": "", "sheet": "单选题"}, {"id": 2, "type": "单选题", "question": "大数据的最显著特征是（）", "options": ["数据规模大", "数据类型多样", "数据处理速度快", "数据价值密度高"], "answer": "A", "analysis": "", "sheet": "单选题"}, {"id": 3, "type": "单选题", "question": "美国海军军官莫里通过对前人航海日志的分析，绘制了新的航海路线图，标明了大风与洋流可能发生的地点。这体现了大数据分析理念中的（ ）", "options": ["在数据基础上倾向于全体数据而不是抽样数据", "在分析方法上更注重相关分析而不是因果分析", "在分析效果上更追究效率而不是绝对精确", "在数据规模上强调相对数据而不是绝对数据"], "answer": "B", "analysis": "", "sheet": "单选题"}, {"id": 4, "type": "单选题", "question": "下列关于舍恩伯格对大数据特点的说法中，错误的是（）", "options": ["数据规模大", "数据类型多样", "数据处理速度快", "数据价值密度高"], "answer": "D", "analysis": "", "sheet": "单选题"}, {"id": 5, "type": "单选题", "question": "当前社会中，最为突出的大数据环境是（ ）", "options": ["互联网", "物联网", "综合国力", "自然资源"], "answer": "A", "analysis": "", "sheet": "单选题"}, {"id": 6, "type": "单选题", "question": "下列关于大数据的分析理念的说法中，错误的是", "options": ["在数据基础上倾向于全体数据而不是抽样数据", "在分析方法上更注重相关分析而不是因果分析", "在分析效果上更追究效率而不是绝对精确", "在数据规模上强调相对数据而不是绝对数据"], "answer": "D", "analysis": "", "sheet": "单选题"}, {"id": 7, "type": "单选题", "question": "大数据时代，数据使用的关键是（  ）", "options": ["数据收集", "数据存储", "数据分析", "数据再利用"], "answer": "D", "analysis": "", "sheet": "单选题"}, {"id": 8, "type": "单选题", "question": "下列论据中，能够支撑“大数据无所不能”的观点的是（ ）", "options": ["互联网金融打破了传统的观念和行为", "大数据存在泡沫", "大数据具有非常高的成本", "个人隐私泄露与信息安全担忧"], "answer": "A", "analysis": "", "sheet": "单选题"}, {"id": 9, "type": "单选题", "question": "关于大数据在社会综合治理中的作用，以下理解不正确的是", "options": ["大数据的运用能够维护社会治安", "大数据的运用能够加强交通管理", "大数据的运用能够杜绝抗生素的滥用", "大数据的运用有利于走群众路线"], "answer": "C", "analysis": "", "sheet": "单选题"}, {"id": 10, "type": "单选题", "question": "面向用户提供大数据一站式部署方案，包括数据中心和服务器等硬件、数据分析应用软件及技术运维支持等多方面内容的大数据商业模式是（）", "options": ["大数据解决方案模式", "大数据信息分类模式", "大数据处理服务模式", "大数据资源提供模式"], "answer": "A", "analysis": "", "sheet": "单选题"}, {"id": 11, "type": "单选题", "question": "以下哪一项属于非结构化数据。（）", "options": ["企业ERP数据", "财务系统数据", "视频监控数据", "日志数据"], "answer": "C", "analysis": "", "sheet": "单选题"}, {"id": 12, "type": "单选题", "question": "下列关于相关性系数（即皮尔逊系数）的说法，正确的有", "options": ["相关性系数的范围在-1到1之间，相关性系数大于0是正相关，小于0是负相关", "相关性系数的越接近于-1，说明x与y的相关性越小", "相关性系数的范围在0到1之间，相关性系数大于0.5是正相关，小于0.5是负相关", "若相关性系数大于1，则说明x与y呈现完全线性相关关系"], "answer": "A", "analysis": "", "sheet": "单选题"}, {"id": 13, "type": "单选题", "question": "用二维表来表示实体与实体之间联系的数据模型称为（）", "options": ["实体—联系模型", "层次模型", "关系模型", "网状模型"], "answer": "C", "analysis": "", "sheet": "单选题"}, {"id": 14, "type": "单选题", "question": "下列哪个不是专门用于可视化时间空间数据的技术 (  )", "options": ["等高线图", "饼图", "曲面图", "矢量场图"], "answer": "B", "analysis": "", "sheet": "单选题"}, {"id": 15, "type": "单选题", "question": "适合绘制时间变化趋势的图形为？", "options": ["饼图", "折线图", "柱状图", "散点图"], "answer": "B", "analysis": "", "sheet": "单选题"}, {"id": 16, "type": "单选题", "question": "适合绘制数量比例的图形为？", "options": ["饼图", "折线图", "柱状图", "散点图"], "answer": "A", "analysis": "", "sheet": "单选题"}, {"id": 17, "type": "单选题", "question": "适合绘制分类数量的图形为？", "options": ["饼图", "折线图", "柱状图", "散点图"], "answer": "C", "analysis": "", "sheet": "单选题"}, {"id": 18, "type": "单选题", "question": "适合观察数据关系的图形为？", "options": ["饼图", "折线图", "柱状图", "散点图"], "answer": "D", "analysis": "", "sheet": "单选题"}, {"id": 19, "type": "单选题", "question": "适合绘制坐标位置的图形为？", "options": ["饼图", "折线图", "柱状图", "散点图"], "answer": "D", "analysis": "", "sheet": "单选题"}, {"id": 20, "type": "单选题", "question": "适合观察数据分布的图形为？", "options": ["饼图", "折线图", "直方图", "散点图"], "answer": "C", "analysis": "", "sheet": "单选题"}, {"id": 21, "type": "单选题", "question": "对于给定天气信息数据集，已知空气的温度、湿度、气压、是否降雨以及pm2.5指数，需要建立一个回归模型预测pm2.5指数，这属于(____)。", "options": ["无监督学习", "半监督学习", "监督学习", "强化学习"], "answer": "C", "analysis": "", "sheet": "单选题"}, {"id": 22, "type": "单选题", "question": "对特征数据进行标准化，以下说法不正确的是(  )。", "options": ["可以使所有特征数据处于相同的大小维度", "可以加快梯度下降的收敛速度", "会使模型出现过拟合", "避免了模型对数据偏差处理"], "answer": "C", "analysis": "", "sheet": "单选题"}, {"id": 23, "type": "单选题", "question": "大数据的本质是(  )", "options": ["洞察", "采集", "统计", "联系"], "answer": "A", "analysis": "", "sheet": "单选题"}, {"id": 24, "type": "单选题", "question": "以下不属于数据科学的三大支柱的是(  )", "options": ["数据学", "逻辑学", "分析学", "算法学"], "answer": "B", "analysis": "", "sheet": "单选题"}, {"id": 25, "type": "单选题", "question": "数据可视化利用的是哪个算法(  )", "options": ["分类", "降维", "回归", "SVM"], "answer": "B", "analysis": "", "sheet": "单选题"}, {"id": 26, "type": "单选题", "question": "数据加工是指(  )", "options": ["收集信息", "将信息用数据表示并按类别组织保存", "对数据进行变换，抽取和运算", "在空间或时间上以各种形式传播信息", "在需要的时候能够提取数据"], "answer": "C", "analysis": "", "sheet": "单选题"}, {"id": 27, "type": "单选题", "question": "（）是数据加工后的表现形式", "options": ["图像", "视频", "音频", "数值"], "answer": "D", "analysis": "", "sheet": "单选题"}, {"id": 28, "type": "单选题", "question": "若不针对MapReduce编程模型中的key和value值进行特别设置，下列哪一项是MapReduce不适宜的运算。", "options": ["Max", "Min", "Count", "Average"], "answer": "D", "analysis": "", "sheet": "单选题"}, {"id": 29, "type": "单选题", "question": "Spark是基于(  )的大数据分布式计算框架", "options": ["内存计算", "硬盘计算", "图像计算", "关系型"], "answer": "A", "analysis": "", "sheet": "单选题"}, {"id": 30, "type": "单选题", "question": "Spark使用(  )语言进行实现", "options": ["C#", "C", "Java", "Scala"], "answer": "D", "analysis": "", "sheet": "单选题"}, {"id": 31, "type": "单选题", "question": "RDD 是一个(  )的数据结构", "options": ["不可扩展且串行", "不可扩展且并行", "可以容错且并行", "可以容错且串行"], "answer": "C", "analysis": "", "sheet": "单选题"}, {"id": 32, "type": "单选题", "question": "RDD的全称是(  )", "options": ["Reserve Dispatch Dataset", "Reserve Distinct DataSource", "Remote Distinct DataSource", "Resilient Distributed Dataset"], "answer": "D", "analysis": "", "sheet": "单选题"}, {"id": 33, "type": "单选题", "question": "返回一个包含元素的新RDD，它满足过滤器内部的功能,用什么api?", "options": ["map", "filter", "collect", "foreach"], "answer": "B", "analysis": "", "sheet": "单选题"}, {"id": 34, "type": "单选题", "question": "Spark拥有(  )执行引擎，支持在内存中对数据进行迭代计算", "options": ["FFMepg", "MapReduce", "Big Table", "DAG"], "answer": "D", "analysis": "", "sheet": "单选题"}, {"id": 35, "type": "单选题", "question": "机器学习的应用包括哪方面（）", "options": ["数据挖掘", "自然语言处理", "计算机视觉", "以上皆是"], "answer": "D", "analysis": "", "sheet": "单选题"}, {"id": 36, "type": "单选题", "question": "下列可以用于聚类问题的机器学习算法有（）", "options": ["决策树", "k-means", "随机森林", "逻辑回归"], "answer": "B", "analysis": "", "sheet": "单选题"}, {"id": 37, "type": "单选题", "question": "在机器学习任务中经常假设矩阵为n×n的对称矩阵A， 则以下说法正确的是(  )", "options": ["对称矩阵为满秩矩阵", "对称矩阵的列向量之间正交", "对应于A的不同特征值的特征向量之间正交", "对应于A的相同特征值得特征向量之间正交"], "answer": "C", "analysis": "", "sheet": "单选题"}, {"id": 38, "type": "单选题", "question": "下面的问题，哪一个属于分类问题的是（）", "options": ["根据员工的薪水、工作压力、成长环境、工作年限、绩效考核等数据，预测员工下一季度的销售额", "根据员工的薪水、工作压力、成长环境、工作年限、绩效考核等数据，预测员工下一季度的绩效考核分数", "根据员工的薪水、工作压力、成长环境、工作年限、绩效考核等数据，预测员工在接下来一段时间内的工资涨幅", "根据员工的薪水、工作压力、成长环境、工作年限、绩效考核等数据，预测员工是否可能会在接下来的一段时间内离职"], "answer": "D", "analysis": "", "sheet": "单选题"}, {"id": 39, "type": "单选题", "question": "逻辑回归一般采用哪个函数来将输出映射在（0，1）区间？", "options": ["square函数", "sigmoid函数", "probit函数", "mode函数"], "answer": "B", "analysis": "", "sheet": "单选题"}, {"id": 40, "type": "单选题", "question": "在评价逻辑回归模型效果时，不采用以下哪种指标（）", "options": ["auc指数", "roc曲线", "f1-score", "mse"], "answer": "D", "analysis": "", "sheet": "单选题"}, {"id": 41, "type": "单选题", "question": "怎么样去诊断算法是否是过拟合？", "options": ["训练误差很小，验证误差较大，高方差。", "训练误差很大，验证误差较大，高方差。", "训练误差和验证误差都很大，高偏差。", "训练误差和验证误差都很小，高偏差。"], "answer": "A", "analysis": "", "sheet": "单选题"}, {"id": 42, "type": "单选题", "question": "怎么样去诊断算法是否是欠拟合？", "options": ["训练误差很小，验证误差较大，高方差。", "训练误差很大，验证误差较大，高方差。", "训练误差和验证误差都很大，高偏差。", "训练误差和验证误差都很小，高偏差。"], "answer": "C", "analysis": "", "sheet": "单选题"}, {"id": 43, "type": "单选题", "question": "PCA是一种（）", "options": ["无监督学习的降维方式", "监督学习的降维方式", "半监督学习的降维方式", "强化学习的降维方式"], "answer": "A", "analysis": "", "sheet": "单选题"}, {"id": 44, "type": "单选题", "question": "经典knn算法中，是根据以下哪项来确定数据点的类别的（）", "options": ["k个邻居点出现次数最多的类别", "k个邻居点出现次数最少的类别", "k个邻居中离该数据点最远的邻居点的类别", "k个邻居中离该数据点最近的邻居点的类别"], "answer": "A", "analysis": "", "sheet": "单选题"}, {"id": 45, "type": "单选题", "question": "下列属于无监督学习的是（\t）", "options": ["KNN", "Logisti Regression", "k-means", "SVM"], "answer": "C", "analysis": "", "sheet": "单选题"}, {"id": 46, "type": "单选题", "question": "下面关于k近邻的说法，正确的是（）", "options": ["k近邻可以用于分类，但是不能用于回归", "根据特征向量X计算样本之间的相似性，选择离中心点最相似的k个样本", "k近邻用于分类时，对于新的样本，计算离其最近的k个样本的平均值，作为新样本的预测值", "k近邻用于分类时，对于新的样本，根据其k个最近邻样本的类别，通过多数表决的方式预测新样本的类别"], "answer": "D", "analysis": "", "sheet": "单选题"}, {"id": 47, "type": "单选题", "question": "考虑这么一种情况：一个对象碰巧与另一个对象相对接近，但属于不同的类，因为这两个对象一般不会共享许多近邻，所以应该选择（  ）的相似度计算方法。", "options": ["平方欧几里德距离", "余弦距离", "直接相似度", "共享最近邻"], "answer": "D", "analysis": "", "sheet": "单选题"}, {"id": 48, "type": "单选题", "question": "决策树进行特征选择时，最优特征是指(  )", "options": ["信息增益最小的特征", "使决策树模型拟合得最好的特征", "使数据集不确定性降低最多的特征", "以上都不对"], "answer": "C", "analysis": "", "sheet": "单选题"}, {"id": 49, "type": "单选题", "question": "下面关于随机森林和集成学习的说法，正确的是（）", "options": ["随机森林只能用于解决分类问题", "集成学习通过构建多个模型，并将各个模型的结果使用求平均数的方法集成起来，作为最终的预测结果，提高分类问题的准确率", "随机森林由随机数量的决策树组成", "随机森林的弱分类器（基分类器）的特征选择不是随机的"], "answer": "B", "analysis": "", "sheet": "单选题"}, {"id": 50, "type": "单选题", "question": "对于L1和L2正则化，以下说法正确的是（）", "options": ["L2正则化对大数更为敏感，得到的是均匀参数", "L2正则化为大数更为敏感，得到的是稀疏参数", "L1正则化对大数更为敏感，得到的是均匀参数", "L1正则化为大数更为敏感，得到的是稀疏参数"], "answer": "A", "analysis": "", "sheet": "单选题"}, {"id": 51, "type": "单选题", "question": "线性回归模型h(x)=wx+b，b代表的是（）", "options": ["均方误差", "误差", "残差", "偏差"], "answer": "D", "analysis": "", "sheet": "单选题"}, {"id": 52, "type": "单选题", "question": "下面关于回归的说法，错误的是（）", "options": ["线性回归是一种经典的回归分析方法", "回归用于分析自变量和应变量之间的关系", "自变量X（也就是特征）往往包含多个特征", "在回归中，建立应变量关于自变量的函数，自变量是应变量在函数上的映射"], "answer": "D", "analysis": "", "sheet": "单选题"}, {"id": 53, "type": "单选题", "question": "在scikit-learn包里，如果想要把字符串类型的类别特征转换成数值型，符合逻辑回归的要求，需要使用（     ）进行转换。", "options": ["Encoder", "Label", "to_float", "LabelEncoder"], "answer": "D", "analysis": "", "sheet": "单选题"}, {"id": 54, "type": "单选题", "question": "假设使用逻辑回归进行n多类别分类，使用 One-vs-rest 分类法。下列说法正确的是(  )", "options": ["对于 n 类别，需要训练 n 个模型", "对于 n 类别，需要训练 n+1 个模型", "对于 n 类别，需要训练 n-1 个模型", "对于 n 类别，只需要训练 1 个模型"], "answer": "A", "analysis": "", "sheet": "单选题"}, {"id": 55, "type": "单选题", "question": "逻辑回归模型是解决什么问题的模型？", "options": ["分类问题", "聚类问题", "回归问题", "降维问题"], "answer": "A", "analysis": "", "sheet": "单选题"}, {"id": 56, "type": "单选题", "question": "当决策树出现过拟合的时候，可以采取以下哪些措施（）", "options": ["剪枝", "增加训练次数", "进行交叉检验", "增加树的深度"], "answer": "A", "analysis": "", "sheet": "单选题"}, {"id": 57, "type": "单选题", "question": "深度神经网络中，隐藏层无法学习的情况被称为（）问题", "options": ["梯度下降", "梯度消失", "梯度爆炸", "梯度发散"], "answer": "B", "analysis": "", "sheet": "单选题"}, {"id": 58, "type": "单选题", "question": "循环神经网络优势在于（）", "options": ["对序列的每个元素进行相同的计算，输出取决于之前的数据状态", "对序列的每个元素进行不同的计算，输出取决于之前的数据状态", "对序列的每个元素进行相同的计算，输出取决于之后的数据状态", "对序列的每个元素进行不同的计算，输出取决于之后的数据状态"], "answer": "A", "analysis": "", "sheet": "单选题"}, {"id": 59, "type": "单选题", "question": "标准循环神经网络隐含层的输入对于网络输出的影响随时间(  )", "options": ["不断递归而衰退", "不断递归而增强", "先增强后减弱", "先减弱后增强"], "answer": "A", "analysis": "", "sheet": "单选题"}, {"id": 60, "type": "单选题", "question": "长短期记忆网络中，当想要剔除之前无用的信息，应采用（）", "options": ["遗忘门", "更新门", "输入门", "输出门"], "answer": "A", "analysis": "", "sheet": "单选题"}, {"id": 61, "type": "单选题", "question": "下列哪一项在神经网络中引入了非线性", "options": ["随机梯度下降", "修正线性单元（ReLU）", "卷积函数", "全连接层"], "answer": "B", "analysis": "", "sheet": "单选题"}, {"id": 62, "type": "单选题", "question": "图像灰度方差说明了图像哪一个属性", "options": ["平均灰度", "图像对比度", "图像整体亮度", "图像细节"], "answer": "B", "analysis": "", "sheet": "单选题"}, {"id": 63, "type": "单选题", "question": "计算机显示器主要采用哪一种彩色模型", "options": ["RGB", "CMY", "CMYK", "HSV"], "answer": "A", "analysis": "", "sheet": "单选题"}, {"id": 64, "type": "单选题", "question": "用模板[-1 1]ᵀ 主要检测(  )方向的边缘", "options": ["水平", "45°", "垂直", "135°"], "answer": "C", "analysis": "", "sheet": "单选题"}, {"id": 65, "type": "单选题", "question": "下列算法中属于图象锐化处理的是(  )", "options": ["低通滤波", "加权平均法", "高通滤波", "中值滤波"], "answer": "C", "analysis": "", "sheet": "单选题"}, {"id": 66, "type": "单选题", "question": "维纳滤波器通常用于(  )", "options": ["去噪", "减小图像动态范围", "复原图像", "平滑图像"], "answer": "C", "analysis": "", "sheet": "单选题"}, {"id": 67, "type": "单选题", "question": "图像平滑处理可以采用RGB彩色模型的是（ )", "options": ["直方图均衡化", "直方图均衡化", "加权均值滤波", "中值滤波"], "answer": "C", "analysis": "", "sheet": "单选题"}, {"id": 68, "type": "单选题", "question": "(  )滤波器在对图像复原过程中需要计算噪声功率谱和图像功率谱", "options": ["逆滤波", "维纳滤波", "约束最小二乘滤波", "同态滤波"], "answer": "B", "analysis": "", "sheet": "单选题"}, {"id": 69, "type": "单选题", "question": "一幅灰度级均匀分布的图象，其灰度范围在[0，255]，则该图象的信息量为(  )", "options": ["0", "255", "6", "8"], "answer": "D", "analysis": "", "sheet": "单选题"}, {"id": 70, "type": "单选题", "question": "下列算法中属于点处理的是", "options": ["梯度锐化", "二值化", "傅立叶变换", "中值滤波"], "answer": "B", "analysis": "", "sheet": "单选题"}, {"id": 71, "type": "单选题", "question": "数字图像处理研究的内容不包括", "options": ["图像数字化", "图像增强", "图像分割", "数字图像存储"], "answer": "D", "analysis": "", "sheet": "单选题"}, {"id": 72, "type": "单选题", "question": "将灰度图像转换成二值图像的命令为", "options": ["ind2gray", "ind2rgb", "im2bw", "ind2bw"], "answer": "C", "analysis": "", "sheet": "单选题"}, {"id": 73, "type": "单选题", "question": "像的形态学处理方法包括", "options": ["图像增强", "图像锐化", "图像分割", "腐蚀"], "answer": "D", "analysis": "", "sheet": "单选题"}, {"id": 74, "type": "单选题", "question": "图象与灰度直方图间的对应关系是", "options": ["一一对应", "多对一", "一对多", "多对多"], "answer": "B", "analysis": "", "sheet": "单选题"}, {"id": 75, "type": "单选题", "question": "下列哪些技术能被用于关键词归一化（keyword normalization），即把关键词转化为其基本形式？", "options": ["词形还原", "探测法", "余弦相似度", "N-grams"], "answer": "A", "analysis": "", "sheet": "单选题"}, {"id": 76, "type": "单选题", "question": "哪些文本分析技术可被用于名词短语检测、动词短语检测、主语检测和宾语检测？", "options": ["词性标注", "Skip Gram 和N-Gram 提取", "连续性词袋", "依存句法分析和成分句法分析"], "answer": "D", "analysis": "", "sheet": "单选题"}, {"id": 77, "type": "单选题", "question": "下面哪个是NLP用例?", "options": ["从图像中检测物体", "面部识别", "语音生物识别", "文本摘要"], "answer": "D", "analysis": "", "sheet": "单选题"}, {"id": 78, "type": "单选题", "question": "下列算法中减少了常用词的权重，增加了文档集合中不常用词的权重的是？", "options": ["词频（TF）", "逆文档频率（IDF）", "Word2Vec", "隐狄利克雷分布"], "answer": "B", "analysis": "", "sheet": "单选题"}, {"id": 79, "type": "单选题", "question": "从句子中删除“and”、“is”、“a”、“an”、“the” 这样的词的过程被称为？", "options": ["词干提取", "词形还原", "停用词", "词频统计"], "answer": "C", "analysis": "", "sheet": "单选题"}, {"id": 80, "type": "单选题", "question": "从给定的句子、段落中识别人名、组织名的过程称为？", "options": ["词干提取", "词性标注", "命名实体识别", "词形还原"], "answer": "C", "analysis": "", "sheet": "单选题"}, {"id": 81, "type": "单选题", "question": "下列哪一项不是预处理技术？", "options": ["词干提取和词形还原", "转换成小写", "删除停用词", "情绪分析"], "answer": "D", "analysis": "", "sheet": "单选题"}, {"id": 82, "type": "单选题", "question": "Hadoop中Zookeeper主要解决的是()。", "options": ["分布式数据一致性问题", "灾备问题", "日志收集分析问题", "结构化数据与hadoop间数据转换问题"], "answer": "A", "analysis": "", "sheet": "单选题"}, {"id": 83, "type": "单选题", "question": "以下哪种情况说明模型出现了过拟合()。", "options": ["模型对训练集拟合程度高，对测试集拟合程度高", "模型对训练集拟合程度高，对测试集拟合程度低", "模型对训练集拟合程度低，对测试集拟合程度高", "模型对训练集拟合程度低，对测试集拟合程度低"], "answer": "B", "analysis": "", "sheet": "单选题"}, {"id": 84, "type": "单选题", "question": "下列是监督学习算法的是()。", "options": ["决策树算法、支持向量机算法、K-近邻算法", "支持向量机算法、K-近邻算法、主成分分析算法", "支持向量机算法、主成分分析算法、K-Means聚类算法", "决策树算法、支持向量机算法、K-Means聚类算法"], "answer": "A", "analysis": "", "sheet": "单选题"}, {"id": 85, "type": "单选题", "question": "下面关于k近邻学习算法的说法，正确的是()。", "options": ["k近邻可以用于分类，但是不能用于回归", "k近邻属于“急切学习”", "k近邻用于分类时，对于新的样本，计算离其最近的k个样本的平均值，作为新样本的预测值", "k近邻用于分类时，对于新的样本，根据其k个最近邻样本的类别，通过多数表决的方式预测新样本的类别"], "answer": "D", "analysis": "", "sheet": "单选题"}, {"id": 86, "type": "单选题", "question": "一组数据有8个特征，计算出其8个特征值从大到小依次为3.755、2.197、1.215、0.402、0.213、0.138、0.065、0.015，若选择累计百分比达到80%以上的特征值对应的主成分，则至少应选择几个主成分()。", "options": ["3", "4", "5", "2"], "answer": "A", "analysis": "", "sheet": "单选题"}, {"id": 87, "type": "单选题", "question": "下列关于正则化说法错误的是()。", "options": ["L1正则化可以用于特征选择", "L1正则化和L2正则化可以减少过拟合", "Lp正则化不能减少过拟合", "L1正则化和L2正则化可以看成是损失函数的惩罚项"], "answer": "C", "analysis": "", "sheet": "单选题"}, {"id": 88, "type": "单选题", "question": "机器学习中L1正则化和L2正则化的区别是()。", "options": ["使用L1可以得到稀疏的权值，使用L2可以得到平滑的权值", "使用L1可以得到平滑的权值，使用L2可以得到平滑的权值", "使用L1可以得到平滑的权值，使用L2可以得到稀疏的权值", "使用L1可以得到稀疏的权值，使用L2可以得到稀疏的权值"], "answer": "A", "analysis": "", "sheet": "单选题"}, {"id": 89, "type": "单选题", "question": "下列关于特征选择说法正确的是()。", "options": ["Relief是一种著名的包裹式特征选择方法", "LVW是一个典型的过滤式特征选择方法", "嵌入式选择是将特征选择过程与学习器训练过程融为一体", "决策树算法在构建树的同时没有进行特征选择"], "answer": "C", "analysis": "", "sheet": "单选题"}, {"id": 90, "type": "单选题", "question": "下列关于线性模型说法正确的是()。", "options": ["ln=wx+b不是线性模型", "线性模型不能用梯度下降求解", "线性模型试图学得一个通过属性的线性组合来预测的函数", "线性回归模型是无监督学习"], "answer": "C", "analysis": "", "sheet": "单选题"}, {"id": 91, "type": "单选题", "question": "构建一个最简单的线性回归模型需要几个系数（只有一个特征）()。", "options": ["1", "2", "3", "4"], "answer": "B", "analysis": "", "sheet": "单选题"}, {"id": 92, "type": "单选题", "question": "下列算法哪一个不是决策树常用算法。", "options": ["ID3", "C4.5", "CART", "LDA"], "answer": "D", "analysis": "", "sheet": "单选题"}, {"id": 93, "type": "单选题", "question": "朴素贝叶斯法属于()。", "options": ["生成模型", "回归模型", "聚类模型", "分类模型"], "answer": "A", "analysis": "", "sheet": "单选题"}, {"id": 94, "type": "单选题", "question": "在朴素贝叶斯法的参数求解过程中，为了解决利用极大似然估计概率值为0的情况，可以采用以下哪种方法。", "options": ["核技巧", "拉普拉斯平滑", "数据标准化", "聚类"], "answer": "B", "analysis": "", "sheet": "单选题"}, {"id": 95, "type": "单选题", "question": "朴素贝叶斯的条件独立假设指的是()。", "options": ["当X确定时，Y的取值是独立的", "当Y确定时，X的各个分量取值之间相互独立", "两个样本Y的取值是独立的", "X的取值与Y的取值是独立的"], "answer": "B", "analysis": "", "sheet": "单选题"}, {"id": 96, "type": "单选题", "question": "神经网络中最基本的成分是()。", "options": ["损失函数", "学习算法", "神经元", "前馈网络"], "answer": "C", "analysis": "", "sheet": "单选题"}, {"id": 97, "type": "单选题", "question": "Apriori算法是用来进行()。", "options": ["关联分析", "数据分类", "数据预处理", "聚类分析"], "answer": "A", "analysis": "", "sheet": "单选题"}, {"id": 98, "type": "单选题", "question": "使用交叉验证法，我们可以()。", "options": ["帮助我们更好的进行模型选择，并在一定程度上减少过拟合", "减少模型计算量", "减少模型复杂度", "更好进行特征选择，使得模型效果更好"], "answer": "A", "analysis": "", "sheet": "单选题"}, {"id": 99, "type": "单选题", "question": "将数据集分为两个互斥的集合，其中一个集合作为训练集，另一个作为测试集，这种对数据集的操作方法称为()。", "options": ["留出法", "交叉验证法", "自助法", "调参法"], "answer": "A", "analysis": "", "sheet": "单选题"}, {"id": 100, "type": "单选题", "question": "F1值，是()和()的调和平均。\n①查准率②查全率③错误率④精度", "options": ["②③", "①③", "①②", "②④"], "answer": "C", "analysis": "", "sheet": "单选题"}, {"id": 101, "type": "单选题", "question": "MapReduce中reduce过程可以想象成()。", "options": ["零件组装", "汽车拆解", "零件替换", "配送"], "answer": "A", "analysis": "", "sheet": "单选题"}, {"id": 102, "type": "单选题", "question": "下列关于过拟合、欠拟合说法正确的是()。", "options": ["样本数量过少容易导致过拟合", "欠拟合是因为模型学习能力过强，以至于把训练样本的不太一般的性质都学到了", "在分类问题中，训练样本都分类正确，而测试样本分类精度为0，这种现象称为欠拟合", "样本数量过多容易导致过拟合"], "answer": "A", "analysis": "", "sheet": "单选题"}, {"id": 103, "type": "单选题", "question": "ID3算法根据()准则选择特征。", "options": ["熵", "信息增益", "信息增益比", "基尼指数"], "answer": "B", "analysis": "", "sheet": "单选题"}, {"id": 104, "type": "单选题", "question": "DBSCAN是基于()的聚类算法。", "options": ["长度", "密度", "能量", "大小"], "answer": "B", "analysis": "", "sheet": "单选题"}, {"id": 105, "type": "单选题", "question": "某超市研究销售纪录数据后发现，买啤酒的人很大概率也会购买尿布，这种属于数据挖掘的哪类问题？", "options": ["关联规则发现", "聚类", "分类", "自然语言处理"], "answer": "A", "analysis": "", "sheet": "单选题"}, {"id": 106, "type": "单选题", "question": "将原始数据进行集成、变换、维度规约、数值规约是在以下哪个步骤的任务？", "options": ["频繁模式挖掘", "分类和预测", "数据预处理", "数据流挖掘"], "answer": "C", "analysis": "", "sheet": "单选题"}, {"id": 107, "type": "单选题", "question": "当不知道数据所带标签时，可以使用哪种技术促使带同类标签的数据与带其他标签的数据相分离？", "options": ["分类", "聚类", "关联分析", "隐马尔可夫链"], "answer": "B", "analysis": "", "sheet": "单选题"}, {"id": 108, "type": "单选题", "question": "什么是KDD？", "options": ["数据挖掘与知识发现", "领域知识发现", "文档知识发现", "动态知识发现"], "answer": "A", "analysis": "", "sheet": "单选题"}, {"id": 109, "type": "单选题", "question": "使用交互式的和可视化的技术，对数据进行探索属于数据挖掘的哪一类任务？", "options": ["探索性数据分析", "建模描述", "预测建模", "寻找模式和规则"], "answer": "A", "analysis": "", "sheet": "单选题"}, {"id": 110, "type": "单选题", "question": "为数据的总体分布建模，把多维空间划分成组等问题属于数据挖掘的哪一类任务？", "options": ["探索性数据分析", "建模描述", "预测建模", "寻找模式和规则"], "answer": "B", "analysis": "", "sheet": "单选题"}, {"id": 111, "type": "单选题", "question": "建立一个模型，通过这个模型根据已知的变量值来预测其他某个变量值属于数据挖掘的哪一类任务？", "options": ["探索性数据分析", "建模描述", "预测建模", "寻找模式和规则"], "answer": "C", "analysis": "", "sheet": "单选题"}, {"id": 112, "type": "单选题", "question": "用户有一种感兴趣的模式并且希望在数据集中找到相似的模式，属于数据挖掘哪一类任务？", "options": ["探索性数据分析", "建模描述", "预测建模", "寻找模式和规则"], "answer": "D", "analysis": "", "sheet": "单选题"}, {"id": 113, "type": "单选题", "question": "下面哪种不属于数据预处理的方法？", "options": ["变量代换", "离散化", "聚集", "估计遗漏值"], "answer": "D", "analysis": "", "sheet": "单选题"}, {"id": 114, "type": "单选题", "question": "假设12个销售价格记录组已经排序如下：5, 10, 11, 13, 15,35, 50, 55, 72, 92, 204, 215 使用如下每种方法将它们划分成四个箱。等频（等深）划分时，15在第几个箱子内？", "options": ["第一个", "第二个", "第三个", "第四个"], "answer": "B", "analysis": "", "sheet": "单选题"}, {"id": 115, "type": "单选题", "question": "以下哪种方法不属于特征选择的标准方法", "options": ["嵌入", "过滤", "包装", "抽样"], "answer": "D", "analysis": "", "sheet": "单选题"}, {"id": 116, "type": "单选题", "question": "下面哪个属于映射数据到新的空间的方法？", "options": ["傅立叶变换", "特征加权", "渐进抽样", "维归约"], "answer": "A", "analysis": "", "sheet": "单选题"}, {"id": 117, "type": "单选题", "question": "假定用于分析的数据包含属性age。数据元组中age的值如下（按递增序）：13，15，16，16，19，20，20，21，22，22，25，25，25，30，33，33，35，35，36，40，45，46，52，70, 问题：使用按箱平均值平滑方法对上述数据进行平滑，箱的深度为3。第二个箱子值为", "options": ["18.3", "22.6", "26.8", "27.9"], "answer": "A", "analysis": "", "sheet": "单选题"}, {"id": 118, "type": "单选题", "question": "在抽样方法中，当合适的样本容量很难确定时，可以使用的抽样方法是", "options": ["有放回的简单随机抽样", "无放回的简单随机抽样", "分层抽样", "渐进抽样"], "answer": "D", "analysis": "", "sheet": "单选题"}, {"id": 119, "type": "单选题", "question": "在图集合中发现一组公共子结构，这样的任务称为", "options": ["频繁子集挖掘", "频繁子图挖掘", "频繁数据项挖掘", "频繁模式挖掘"], "answer": "B", "analysis": "", "sheet": "单选题"}, {"id": 120, "type": "单选题", "question": "以下哪些算法是分类算法", "options": ["DBSCAN", "C4.5", "K-Mean", "EM"], "answer": "B", "analysis": "", "sheet": "单选题"}, {"id": 121, "type": "单选题", "question": "以下哪些分类方法可以较好地避免样本的不平衡问题", "options": ["KNN", "SVM", "Bayes", "神经网络"], "answer": "A", "analysis": "", "sheet": "单选题"}, {"id": 122, "type": "单选题", "question": "决策树中不包含一下哪种结点", "options": ["根结点", "内部结点", "外部结点", "叶结点"], "answer": "C", "analysis": "", "sheet": "单选题"}, {"id": 123, "type": "单选题", "question": "以下哪项关于决策树的说法是错误的", "options": ["冗余属性不会对决策树的准确率造成不利的影响", "子树可能在决策树中重复多次", "决策树算法对于噪声的干扰非常敏感", "寻找最佳决策树是NP完全问题"], "answer": "C", "analysis": "", "sheet": "单选题"}, {"id": 124, "type": "单选题", "question": "在基于规则分类器的中，依据规则质量的某种度量对规则排序，保证每一个测试记录都是由覆盖它的“最好的”规格来分类，这种方案称为", "options": ["基于类的排序方案", "基于规则的排序方案", "基于度量的排序方案", "基于规格的排序方案"], "answer": "B", "analysis": "", "sheet": "单选题"}, {"id": 125, "type": "单选题", "question": "以下哪些算法是基于规则的分类器", "options": ["C4.5", "KNN", "Bayes", "ANN"], "answer": "A", "analysis": "", "sheet": "单选题"}, {"id": 126, "type": "单选题", "question": "如果规则集R中不存在两条规则被同一条记录触发，则称规则集R中的规则为", "options": ["无序规则", "穷举规则", "互斥规则", "有序规则"], "answer": "C", "analysis": "", "sheet": "单选题"}, {"id": 127, "type": "单选题", "question": "如果对属性值的任一组合，R中都存在一条规则加以覆盖，则称规则集R中的规则为", "options": ["无序规则", "穷举规则", "互斥规则", "有序规则"], "answer": "B", "analysis": "", "sheet": "单选题"}, {"id": 128, "type": "单选题", "question": "如果规则集中的规则按照优先级降序排列，则称规则集是", "options": ["无序规则", "穷举规则", "互斥规则", "有序规则"], "answer": "D", "analysis": "", "sheet": "单选题"}, {"id": 129, "type": "单选题", "question": "如果允许一条记录触发多条分类规则，把每条被触发规则的后件看作是对相应类的一次投票，然后计票确定测试记录的类标号，称为", "options": ["无序规则", "穷举规则", "互斥规则", "有序规则"], "answer": "A", "analysis": "", "sheet": "单选题"}, {"id": 130, "type": "单选题", "question": "以下关于人工神经网络（ANN）的描述错误的有（ ）", "options": ["神经网络对训练数据中的噪声非常鲁棒", "可以处理冗余特征", "训练ANN是一个很耗时的过程", "至少含有一个隐藏层的多层神经网络"], "answer": "A", "analysis": "", "sheet": "单选题"}, {"id": 131, "type": "单选题", "question": "通过聚集多个分类器的预测来提高分类准确率的技术称为（ ）", "options": ["组合(ensemble)", "聚集(aggregate)", "合并(combination)", "投票(voting)"], "answer": "A", "analysis": "", "sheet": "单选题"}, {"id": 132, "type": "单选题", "question": "简单地将数据对象集划分成不重叠的子集，使得每个数据对象恰在一个子集中，这种聚类类型称作（ ）", "options": ["层次聚类", "划分聚类", "非互斥聚类", "模糊聚类"], "answer": "B", "analysis": "", "sheet": "单选题"}, {"id": 133, "type": "单选题", "question": "在基本K均值算法里，当邻近度函数采用（  ）的时候，合适的质心是簇中各点的中位数", "options": ["曼哈顿距离", "平方欧几里德距离", "余弦距离", "Bregman散度"], "answer": "A", "analysis": "", "sheet": "单选题"}, {"id": 134, "type": "单选题", "question": "（   ）是一个观测值，它与其他观测值的差别如此之大，以至于怀疑它是由不同的机制产生的。", "options": ["边界点", "质心", "离群点", "核心点"], "answer": "C", "analysis": "", "sheet": "单选题"}, {"id": 135, "type": "单选题", "question": "检测一元正态分布中的离群点，属于异常检测中的基于（  ）的离群点检测。", "options": ["统计方法", "邻近度", "密度", "聚类技术"], "answer": "A", "analysis": "", "sheet": "单选题"}, {"id": 136, "type": "单选题", "question": "（  ）将两个簇的邻近度定义为不同簇的所有点对的平均逐对邻近度，它是一种凝聚层次聚类技术", "options": ["MIN（单链）", "MAX（全链）", "组平均", "Ward方法"], "answer": "C", "analysis": "", "sheet": "单选题"}, {"id": 137, "type": "单选题", "question": "（  ）将两个簇的邻近度定义为两个簇合并时导致的平方误差的增量，它是一种凝聚层次聚类技术。", "options": ["MIN（单链）", "MAX（全链）", "组平均", "Ward方法"], "answer": "D", "analysis": "", "sheet": "单选题"}, {"id": 138, "type": "单选题", "question": "DBSCAN在最坏情况下的时间复杂度是( )", "options": ["O(m)", "O(m²)", "O(log m)", "O(m*log m)"], "answer": "B", "analysis": "", "sheet": "单选题"}, {"id": 139, "type": "单选题", "question": "以下属于可伸缩聚类算法的是( )", "options": ["CURE", "DENCLUE", "CLIQUE", "OPOSSUM"], "answer": "A", "analysis": "", "sheet": "单选题"}, {"id": 140, "type": "单选题", "question": "以下哪个聚类算法不是属于基于原型的聚类( )", "options": ["模糊c均值", "EM算法", "SOM", "CLIQUE"], "answer": "D", "analysis": "", "sheet": "单选题"}, {"id": 141, "type": "单选题", "question": "以下哪个聚类算法不属于基于网格的聚类算法( )", "options": ["STING", "WaveCluster", "MAFIA", "BIRCH"], "answer": "D", "analysis": "", "sheet": "单选题"}, {"id": 142, "type": "单选题", "question": "一个对象的离群点得分是该对象周围密度的逆。这是基于（  ）的离群点定义", "options": ["概率", "邻近度", "密度", "聚类"], "answer": "C", "analysis": "", "sheet": "单选题"}, {"id": 143, "type": "单选题", "question": "如下哪些不是最近邻分类器的特点（ ）", "options": ["它使用具体的训练实例进行预测，不必维护源自数据的模型", "分类一个测试样例开销很大", "最近邻分类器基于全局信息进行预测", "可以生产任意形状的决策边界"], "answer": "C", "analysis": "", "sheet": "单选题"}, {"id": 144, "type": "单选题", "question": "HDfS 中的 block 默认保存（ ）份", "options": ["3", "2", "1", "10"], "answer": "A", "analysis": "", "sheet": "单选题"}, {"id": 145, "type": "单选题", "question": "下列哪项通常是集群的最主要瓶颈（ ）", "options": ["CPU", "网络", "磁盘 IO", "内存"], "answer": "C", "analysis": "", "sheet": "单选题"}, {"id": 146, "type": "单选题", "question": "下面与 HDFS 类似的框架是（ ）", "options": ["NTFS", "FAT32", "GFS", "EXT4"], "answer": "C", "analysis": "", "sheet": "单选题"}, {"id": 147, "type": "单选题", "question": "下列哪项关于模型能力（model capacity）的描述是正确的？（指神经网络模型能拟合复杂函数的能力）", "options": ["隐藏层层数增加，模型能力增加", "Dropout的比例增加，模型能力增加", "学习率增加，模型能力增加", "训练轮数（epoch）增加，模型能力增加"], "answer": "A", "analysis": "", "sheet": "单选题"}, {"id": 148, "type": "单选题", "question": "在训练神经网络时，损失函数(loss)在最初的几个epochs时没有下降，可能的原因是（ ）", "options": ["学习率(learning rate)太低", "正则参数太高", "陷入局部最小值", "以上都有可能"], "answer": "D", "analysis": "", "sheet": "单选题"}, {"id": 149, "type": "单选题", "question": "如果你有10,000,000个例子，你会如何划分训练/开发/测试集？", "options": ["33%训练，33%开发，33%测试", "60%训练，20%开发，20%测试", "98%训练，1%开发，1%测试"], "answer": "C", "analysis": "", "sheet": "单选题"}, {"id": 150, "type": "单选题", "question": "开发和测试集应该（ ）", "options": ["来自同一分布", "来自不同分布", "完全相同（一样的(x, y)对）", "数据数量应该相同"], "answer": "A", "analysis": "", "sheet": "单选题"}, {"id": 151, "type": "单选题", "question": "为什么要对输入x进行归一化（ ）", "options": ["让参数初始化更快", "让代价函数更快地优化", "更容易做数据可视化", "是另一种正则化—有助减少方差"], "answer": "B", "analysis": "", "sheet": "单选题"}, {"id": 152, "type": "单选题", "question": "你正在做误差分析并计算错误率，在这些数据集中，你认为你应该手动仔细地检查哪些图片（）", "options": ["随机选择10,000图片", "随机选择500图片", "500张算法分类错误的图片", "10,000张算法分类错误的图片"], "answer": "C", "analysis": "", "sheet": "单选题"}, {"id": 153, "type": "单选题", "question": "在Python中，如何输出文本到控制台？", "options": ["print(\"Hello, World!\")", "print(\"Hello, World!\")；", "System.out.println(\"Hello, World!\")", "printf(\"Hello, World!\")"], "answer": "A", "analysis": "", "sheet": "单选题"}, {"id": 154, "type": "单选题", "question": "下面哪个不是Python的合法标识符？", "options": ["my_variable", "_variable", "123variable", "Variable123"], "answer": "C", "analysis": "", "sheet": "单选题"}, {"id": 155, "type": "单选题", "question": "在Python中，如何获取用户输入？", "options": ["input()", "console.log()", "System.in()", "scanf()"], "answer": "A", "analysis": "", "sheet": "单选题"}, {"id": 156, "type": "单选题", "question": "下面哪个选项是Python的注释符号？", "options": ["//", "--", "/*", "#"], "answer": "D", "analysis": "", "sheet": "单选题"}, {"id": 157, "type": "单选题", "question": "下面哪个选项可以用于创建一个空列表？", "options": ["[]", "{}", "()", "\"\""], "answer": "A", "analysis": "", "sheet": "单选题"}, {"id": 158, "type": "单选题", "question": "在Python中，如何获取字符串的长度？", "options": ["length()", "count()", "size()", "len()"], "answer": "D", "analysis": "", "sheet": "单选题"}, {"id": 159, "type": "单选题", "question": "下面哪个选项用于向列表末尾添加一个元素？", "options": ["insert()", "append()", "extend()", "add()"], "answer": "B", "analysis": "", "sheet": "单选题"}, {"id": 160, "type": "单选题", "question": "下面哪个选项可以用于将一个列表按照特定顺序进行排序？", "options": ["sort()", "arrange()", "order()", "organize()"], "answer": "A", "analysis": "", "sheet": "单选题"}, {"id": 161, "type": "单选题", "question": "下面哪个选项用于删除字典中的键值对？", "options": ["delete()", "remove()", "pop()", "discard()"], "answer": "C", "analysis": "", "sheet": "单选题"}, {"id": 162, "type": "单选题", "question": "DataFrame 和 RDD 最大的区别", "options": ["科学统计支持", "多了 schema", "存储方式不一样", "外部数据源支持"], "answer": "B", "analysis": "", "sheet": "单选题"}, {"id": 163, "type": "单选题", "question": "下列关于MapReduce说法不正确的是", "options": ["MapReduce是一种计算框架", "MapReduce来源于google的学术论文", "MapReduce程序只能用java语言编写", "MapReduce隐藏了并行计算的细节，方便使用"], "answer": "C", "analysis": "", "sheet": "单选题"}, {"id": 164, "type": "单选题", "question": "双样本t检验的常见用法是：", "options": ["通常用于样本含量较大的情况", "用于比较两组样本的均值是否一致", "用于比较两组大样本的成数是否一致", "用于比较两组小样本的方差是否一致"], "answer": "B", "analysis": "", "sheet": "单选题"}, {"id": 165, "type": "单选题", "question": "一个射手连续射靶 22 次，其中 3 次射中 10 环，7 次射中 9 环，9 次射中 8 环，3 次射中 7 环．则射中环数的中位数和众数分别为（ ）", "options": ["8，9", "8，8", "8．5，8", "8．5，9"], "answer": "B", "analysis": "", "sheet": "单选题"}, {"id": 166, "type": "单选题", "question": "支持向量是指（）", "options": ["远离决策平面的数据点", "靠近决策平面的数据点", "支持分类结果的数据点", "不支持分类结果的数据点"], "answer": "B", "analysis": "", "sheet": "单选题"}, {"id": 167, "type": "单选题", "question": "open函数中，参数'wb'的含义是（\t）。", "options": ["创建并二进制只读", "创建并只写方式", "创建并二进制写入", "创建并追加方式"], "answer": "C", "analysis": "", "sheet": "单选题"}, {"id": 168, "type": "单选题", "question": "关于 SecondaryNameNode 下面哪项是正确的", "options": ["它是 NameNode 的热备", "它对内存没有要求", "它的目的是帮助 NameNode 合并编辑日志，减少 NameNode 启动时间", "SecondaryNameNode 应与 NameNode 部署到一个节点"], "answer": "C", "analysis": "", "sheet": "单选题"}, {"id": 169, "type": "单选题", "question": "以下的场景中，适合使用聚类算法的是：", "options": ["根据顾客的年龄、收入、职业、购买频率、购买习惯等相关信息，预测顾客的消费额", "据顾客的年龄、收入、职业、购买频率、购买习惯等相关信息，预测顾客是否会重复购买", "根据顾客的年龄、收入、职业、购买频率、购买习惯等相关信息，把顾客分成不同顾客群体，针对不同的顾客群体采取针对性强的产品推广方法", "据顾客的年龄、收入、职业、购买频率、购买习惯等相关信息，给顾客推荐不同的商品"], "answer": "C", "analysis": "", "sheet": "单选题"}, {"id": 170, "type": "单选题", "question": "下列关于计算机存储容量单位的说法中，错误的是（ ）", "options": ["1KB＜1MB＜1GB", "基本单位是字节（Byte）", "一个汉字需要一个字节的存储空间", "一个字节能够容纳一个英文字符"], "answer": "C", "analysis": "", "sheet": "单选题"}, {"id": 171, "type": "单选题", "question": "（ ）反映数据的精细化程度，越细化的数据，价值越高。", "options": ["规模", "活性", "关联度", "颗粒度"], "answer": "D", "analysis": "", "sheet": "单选题"}, {"id": 172, "type": "单选题", "question": "下列时间序列模型中，哪一个模型可以较好地拟合波动性的分析和预测（）", "options": ["ARMA模型", "AR模型", "MA模型", "GARCH模型"], "answer": "D", "analysis": "", "sheet": "单选题"}, {"id": 173, "type": "单选题", "question": "不是数据预处理的方法是（\t）", "options": ["训练模型", "填充缺失值", "标准化", "归一化"], "answer": "A", "analysis": "", "sheet": "单选题"}, {"id": 174, "type": "单选题", "question": "下面关于Jarvis－Patrik（JP）聚类算法的说法不正确的是（  ）。", "options": ["JP聚类擅长处理噪声和离群点，并且能够处理不同大小、形状和密度的簇。", "JP算法对高维数据效果良好，尤其擅长发现强相关对象的紧致簇。", "JP聚类是基于SNN相似度的概念。", "JP聚类的基本时间复杂度为O(m)。"], "answer": "D", "analysis": "", "sheet": "单选题"}, {"id": 175, "type": "单选题", "question": "在课程视频中，使用随机森林对iris花进行分类，rf = ensemble.RandomForestClassifier()括号中的参数设置为10时，准确率为97.3%，设置为150时，准确率却降低为96%，说明：", "options": ["随着基分类器的增加，模型的泛化误差增大", "150还是小了，应该增大此参数", "随机森林的每个基分类器的特征选择具有一定的随机性", "这是运行错误，因为基分类器越多，分类的性能越好"], "answer": "C", "analysis": "", "sheet": "单选题"}, {"id": 176, "type": "单选题", "question": "ax.legend(loc='best')表示什么？", "options": ["图例为best", "图例位置在右上角", "自动选择图例的最佳位置"], "answer": "C", "analysis": "", "sheet": "单选题"}, {"id": 177, "type": "单选题", "question": "pd.read_csv函数中，指定参数chunksize=50是指", "options": ["随机读取50行数据", "迭代读取数据，每次读取50行", "读取50次数据", "读取前50行数据"], "answer": "B", "analysis": "", "sheet": "单选题"}, {"id": 178, "type": "单选题", "question": "ax1.hist(randn(100),bins=20,color='k',alpha=0.3)表示什么？", "options": ["在ax1上绘制饼图", "在ax1上绘制折线图", "在ax1上绘制直方图"], "answer": "C", "analysis": "", "sheet": "单选题"}, {"id": 179, "type": "单选题", "question": "Python内置函数_______可以返回列表、元组、字典、集合、字符串以及range对象中元素个数。", "options": ["len()", "length", "sizeof()", "max()"], "answer": "A", "analysis": "", "sheet": "单选题"}, {"id": 180, "type": "单选题", "question": "HFile数据格式中的MetaIndex字段用于（）", "options": ["Meta块的长度", "Meta块的结束点", "Meta块数据内容", "Meta块的起始点"], "answer": "D", "analysis": "", "sheet": "单选题"}, {"id": 181, "type": "单选题", "question": "下列方法中，用于获取当前目录的是", "options": ["open", "write", "Getpwd", "read"], "answer": "C", "analysis": "", "sheet": "单选题"}, {"id": 182, "type": "单选题", "question": "已知 x = 3，那么执行语句 x *= 6 之后，x的值为_________。", "options": ["18", "9", "3", "2"], "answer": "A", "analysis": "", "sheet": "单选题"}, {"id": 183, "type": "单选题", "question": "使用PyMySQL建立Python与MySQL之间的连接时，默认以 ___________的方式返回查询结果:", "options": ["字典", "元组", "字符串", "集合"], "answer": "B", "analysis": "", "sheet": "单选题"}, {"id": 184, "type": "单选题", "question": "表达式 list(range(5)) 的值为________。", "options": ["[0, 1, 2, 3, 4]", "[1, 2, 3, 4, 5]", "[0, 1, 2, 3, 4, 5]", "[1,2,3,4]"], "answer": "A", "analysis": "", "sheet": "单选题"}, {"id": 185, "type": "单选题", "question": "pyeharts中，ootstrap默认会将屏幕分为（\t）", "options": ["14份", "12份", "10份", "16份"], "answer": "B", "analysis": "", "sheet": "单选题"}, {"id": 186, "type": "单选题", "question": "已知x=3和y=5，执行语句 x, y = y, x 后x的值是____。", "options": ["5", "3", "4"], "answer": "A", "analysis": "", "sheet": "单选题"}, {"id": 187, "type": "单选题", "question": "HDFS2.x 默认 Block Size大小是多少。", "options": ["32MB", "64MB", "128MB", "256MB"], "answer": "C", "analysis": "", "sheet": "单选题"}, {"id": 188, "type": "单选题", "question": "使用pip命令在线安装扩展库Scikit-learn的完整命令是？", "options": ["pip install scikit-learn", "pip install scikit", "pip install Scikit-learn"], "answer": "A", "analysis": "", "sheet": "单选题"}, {"id": 189, "type": "单选题", "question": "使用sqlite3工具包连接Python和SQLite，如果返回的符合过滤条件的查询结果有多条记录，这个结果默认会以 ______方式返回，里面每条记录是一个。", "options": ["列表，列表", "列表，元组", "元组，元组", "元组，列表"], "answer": "B", "analysis": "", "sheet": "单选题"}, {"id": 190, "type": "单选题", "question": "在Python中，单样本Z检验可以通过（）包来实现。", "options": ["numpy", "pandas", "stats", "statsmodels"], "answer": "D", "analysis": "", "sheet": "单选题"}, {"id": 191, "type": "单选题", "question": "Hadoop配置文件中，hadoop-site.xml显示覆盖hadoop-default.xml里的内容。在版本0.20中，hadoop-site.xml被分离成三个XML文件，不包括", "options": ["conf-site.xml", "mapred-site.xml", "core-site.xml", "hdfs-site.xml"], "answer": "A", "analysis": "", "sheet": "单选题"}, {"id": 192, "type": "单选题", "question": "下列代码执行结果是? [i**i for i in range(3)]", "options": ["[1, 1, 4]", "[0, 1, 4]", "[1, 2, 3]", "(1, 1, 4)"], "answer": "A", "analysis": "", "sheet": "单选题"}, {"id": 193, "type": "单选题", "question": "下列关于distinct关键字的说法正确的是：", "options": ["去重，过滤掉多余的重复记录", "限制输出，只返回一条查询结果", "返回位于表格的第一条记录", "返回所有符合条件的结果"], "answer": "A", "analysis": "", "sheet": "单选题"}, {"id": 194, "type": "单选题", "question": "如果将一组数据中的每一个数都乘以一个非零常数，那么该组数据的（ ）", "options": ["平均数改变，方差不变", "平均数改变，方差改变", "平均数不变，方差改变", "平均数不变，方差不变"], "answer": "B", "analysis": "", "sheet": "单选题"}, {"id": 195, "type": "单选题", "question": "2*1的数组与1*3的数组相加结果为（\t）。", "options": ["2*3的数组", "1*1的数组", "3*2的数组", "以上都不对"], "answer": "A", "analysis": "", "sheet": "单选题"}, {"id": 196, "type": "单选题", "question": "如果一名NBA篮球运动员在某次总决赛的7场比赛中的得分为11，30，17，7，12，34，17，可以使用（ ）来描述这名运动员在这次总决赛中发挥的稳定程度，值越（ ）说明他发挥的稳定性越好。", "options": ["中位数，大", "众数，大", "标准差，小", "平均值，大"], "answer": "C", "analysis": "", "sheet": "单选题"}, {"id": 197, "type": "单选题", "question": "HBase依赖（）提供强大的计算能力", "options": ["Zookeeper", "Chubby", "RPC", "MapReduce"], "answer": "D", "analysis": "", "sheet": "单选题"}, {"id": 198, "type": "单选题", "question": "HBase依赖（）提供消息通信机制", "options": ["Zookeeper", "Chubby", "RPC", "Socket"], "answer": "A", "analysis": "", "sheet": "单选题"}, {"id": 199, "type": "单选题", "question": "Spark提交jar包时所用的命令是什么", "options": ["spark-submit", "submit", "shspark", "jar spark"], "answer": "A", "analysis": "", "sheet": "单选题"}, {"id": 200, "type": "单选题", "question": "下面哪个操作肯定是宽依赖", "options": ["map", "flatMap", "reduceByKey", "sample"], "answer": "C", "analysis": "", "sheet": "单选题"}, {"id": 201, "type": "单选题", "question": "读取文件时并指定文件以空格分隔，则应该添加", "options": ["sep=\"\\n”", "sep=\"\\t”", "sep=\" \"", "sep=\"\\r”"], "answer": "C", "analysis": "", "sheet": "单选题"}, {"id": 202, "type": "单选题", "question": "若λ₀是矩阵A 特征方程的3重根，A的属于λ₀的线性无关的特征向量的个数为k，那么必定有（  ）", "options": ["k=3", "k<=3", "k>3", "k<3"], "answer": "B", "analysis": "", "sheet": "单选题"}, {"id": 203, "type": "单选题", "question": "HDFS默认的当前工作目录是/user/$USER，fs.default.name的值需要在哪个配置文件内说明", "options": ["mapred-site.xml", "core-site.xml", "hdfs-site.xml", "以上均不是"], "answer": "B", "analysis": "", "sheet": "单选题"}, {"id": 204, "type": "单选题", "question": "以下说法正确的是", "options": ["counter方法可以应对数据量更大的的情况，因此应用范围更广", "get方法只能使用在类似列表的数据类型上", "counter方法可以使用在所有迭代的对象上", "get方法可以使用在所有迭代的对象上"], "answer": "D", "analysis": "", "sheet": "单选题"}, {"id": 205, "type": "单选题", "question": "在HTML的表格中，如果需要定义表格的单元格内文字和边缘的空间，需要通过哪个属性来实现？", "options": ["colspan属性", "cellpadding属性", "rowspan属性", "cellspacing属性"], "answer": "B", "analysis": "", "sheet": "单选题"}, {"id": 206, "type": "单选题", "question": "甲、乙、丙、丁四人的数学测验成绩分别为 90 分、90 分、x 分、80 分，若这组数据的 众数与平均数恰好相等，则这组数据的中位数是（ ）", "options": ["100 分", "95 分", "90 分", "85 分"], "answer": "C", "analysis": "", "sheet": "单选题"}, {"id": 207, "type": "单选题", "question": "对于凝聚的层次聚类算法性能，以下说法不正确的是（）", "options": ["适用于大数据集", "算法简单，会遇到合并点选择困难的情况", "一旦一组对象被合并，不能撤销", "以上说法均不正确"], "answer": "A", "analysis": "", "sheet": "单选题"}, {"id": 208, "type": "单选题", "question": "import pandas as pd\ndf1 = pd.Dataframe([[5, 2, 3], [4, 5, 6],[7,8,9]])  \n 其中df1.loc[1,2]=", "options": ["2", "3", "4", "6"], "answer": "D", "analysis": "", "sheet": "单选题"}, {"id": 209, "type": "单选题", "question": "numpy中矩阵转成向量使用", "options": ["reshape", "reval", "arange", "random"], "answer": "B", "analysis": "", "sheet": "单选题"}, {"id": 210, "type": "单选题", "question": "a={2:3},get(2,4)返回的值是（）", "options": ["None", "4", "2", "3"], "answer": "D", "analysis": "", "sheet": "单选题"}, {"id": 211, "type": "单选题", "question": "在循环语句中，_______语句的作用是提前进入下一次循环。", "options": ["break", "continue", "return", "pass"], "answer": "B", "analysis": "", "sheet": "单选题"}, {"id": 212, "type": "单选题", "question": "某班七个兴趣小组人数分别为：3，3，4，4，5，5，6，则这组数据的中位数是（ ）", "options": ["2", "4", "4.5", "5"], "answer": "B", "analysis": "", "sheet": "单选题"}, {"id": 213, "type": "单选题", "question": "出现在datanode的VERSION文件格式中但不出现在namenode的VERSION文件格式中的是", "options": ["namespaceID", "storageID", "storageType", "layoutVersion"], "answer": "B", "analysis": "", "sheet": "单选题"}, {"id": 214, "type": "单选题", "question": "字典对象的_____方法返回字典的“键”列表。", "options": ["keySet()", "keys()", "values()", "list()"], "answer": "B", "analysis": "", "sheet": "单选题"}, {"id": 215, "type": "单选题", "question": "关于K均值和DBSCAN的比较，以下说法不正确的是（  ）。", "options": ["K均值丢弃被它识别为噪声的对象，而DBSCAN一般聚类所有对象。", "K均值使用簇的基于原型的概念，而DBSCAN使用基于密度的概念。", "K均值很难处理非球形的簇和不同大小的簇，DBSCAN可以处理不同大小和不同形状的簇。", "K均值可以发现不是明显分离的簇，即便簇有重叠也可以发现，但是DBSCAN会合并有重叠的簇。"], "answer": "A", "analysis": "", "sheet": "单选题"}, {"id": 216, "type": "单选题", "question": "下列关于特征选择的说法，正确的有：", "options": ["特征选择可以简化模型，但是会增加模型训练时间", "如果使用特征集合X中跟预测目标y负相关的特征去训练模型，可能会降低模型的预测准确率", "特征集合X中可能包含很多冗余或者跟预测目标y无关的特征，所以需要进行特征选择", "特征选择的方法主要基于领域专家内的历史经验"], "answer": "C", "analysis": "", "sheet": "单选题"}, {"id": 217, "type": "单选题", "question": "若两个Dataframe里的索引不完全一致，对这两个Dataframe直接用符号执行相加运算时", "options": ["相同索引里的数值进行相加，不同索引中的数值为Null", "相同索引里的数值进行相加，不同索引中的数值保留为原索引里的数值", "程序报错，不能执行相加运算", "相同索引里的数值进行相加，不同索引中的数值置为NaN"], "answer": "D", "analysis": "", "sheet": "单选题"}, {"id": 218, "type": "单选题", "question": "ax.spines['right'].set_color('none')表示什么？", "options": ["得到当前坐标轴", "隐藏当前坐标轴", "设置右边框为黑色", "将坐标轴移到右侧"], "answer": "B", "analysis": "", "sheet": "单选题"}, {"id": 219, "type": "单选题", "question": "numpy.arange(0,4)的结果为（\t）", "options": ["array([0, 1, 2, 3])", "array[0, 1, 2, 3]", "[0, 1, 2, 3]", "array([0, 1, 2, 3, 4])"], "answer": "A", "analysis": "", "sheet": "单选题"}, {"id": 220, "type": "单选题", "question": "ax1=fig.add_subplot(2,2,1)表示什么？", "options": ["调用第1个子图", "删除第一个子图", "增加一个子图"], "answer": "C", "analysis": "", "sheet": "单选题"}, {"id": 221, "type": "单选题", "question": "在关系数据库系统中，为了简化用户的查询操作，而又不增加数据的存储空间，常用的方法是创建", "options": ["另一个表（TABLE）", "游标（CURSOR）", "视图（VIEW）", "索引（INDEX）"], "answer": "C", "analysis": "", "sheet": "单选题"}, {"id": 222, "type": "单选题", "question": "关于Hadoop单机模式和伪分布式模式的说法，正确的是", "options": ["两者都起守护进程，且守护进程运行在一台机器上", "单机模式不使用HDFS，但加载守护进程", "两者都不与守护进程交互，避免复杂性", "后者比前者增加了HDFS输入输出以及可检查内存使用情况"], "answer": "D", "analysis": "", "sheet": "单选题"}, {"id": 223, "type": "单选题", "question": "Dataframe之间的运算，要求", "options": ["隐式的顺序索引对齐", "隐式顺序索引对齐的优先级高于自定义索引对齐", "两种对齐方式都可以", "自定义索引对齐"], "answer": "D", "analysis": "", "sheet": "单选题"}, {"id": 224, "type": "单选题", "question": "哪个不是DDL(数据库定义语言)语句？", "options": ["ALTER", "CREATE", "CREATE", "GRANT"], "answer": "D", "analysis": "", "sheet": "单选题"}, {"id": 225, "type": "单选题", "question": "pandas.concat函数中，若指定参数axis=1, join='inner',则：", "options": ["保留连接后为空的所在行", "抛弃连接后为空的所在列", "抛弃连接后为空的所在行", "保留连接后为空的所在行和列"], "answer": "C", "analysis": "", "sheet": "单选题"}, {"id": 226, "type": "单选题", "question": "HTML文件中的图片标签<img>属性border指的是：", "options": ["宽度", "图片路径", "边框宽度", "边界"], "answer": "C", "analysis": "", "sheet": "单选题"}, {"id": 227, "type": "单选题", "question": "在seaborn包中，绘制条形图是通过什么方法实现的？", "options": ["distplot()", "barplot()", "histplot()", "boxplot()"], "answer": "B", "analysis": "", "sheet": "单选题"}, {"id": 228, "type": "单选题", "question": "数据仓库的最终目的是（ ）", "options": ["收集业务需求", "建立数据仓库逻辑模型", "开发数据仓库的应用分析", "为用户和业务部门提供决策支持"], "answer": "D", "analysis": "", "sheet": "单选题"}, {"id": 229, "type": "单选题", "question": "EM算法可以用来处理以下哪种问题（）", "options": ["部分数据不可用的问题", "含有隐变量的问题", "有缺失数据的问题", "以上都可以"], "answer": "D", "analysis": "", "sheet": "单选题"}, {"id": 230, "type": "单选题", "question": "假设检验是使用关于（）所提供的证据来决定接受或不接受有关总体的声明", "options": ["数据样本", "数据总体", "简单随机抽样", "一部分数据"], "answer": "A", "analysis": "", "sheet": "单选题"}, {"id": 231, "type": "单选题", "question": "表现较好与表现一般的模型，一般采取哪种方式来获取更好的模拟结果（）", "options": ["相对多数投票", "绝对多数投票", "加权投票", "简单平均"], "answer": "C", "analysis": "", "sheet": "单选题"}, {"id": 232, "type": "单选题", "question": "下面哪个超参数的增加可能会造成随机森林过拟合（）", "options": ["随机种子数", "学习速率", "树的深度", "树的数量"], "answer": "C", "analysis": "", "sheet": "单选题"}, {"id": 233, "type": "单选题", "question": "HDFS是基于流数据模式访问和处理超大文件的需求而开发的，具有高容错、高可靠性、高可扩展性、高吞吐率等特征，适合的读写任务是", "options": ["一次写入，少次读", "多次写入，少次读", "多次写入，多次读", "一次写入，多次读"], "answer": "D", "analysis": "", "sheet": "单选题"}, {"id": 234, "type": "多选题", "question": "按照数据的存储形式，企业数据可以被分为（）", "options": ["结构化数据", "非结构化数据", "半结构化数据", "数字数据"], "answer": "ABC", "analysis": "", "sheet": "多选题"}, {"id": 235, "type": "多选题", "question": "哪些是数据可视化的步骤", "options": ["数据采集", "数据处理", "数据映射", "数据预测"], "answer": "ABC", "analysis": "", "sheet": "多选题"}, {"id": 236, "type": "多选题", "question": "哪些是数据分析的步骤", "options": ["确认需求与课题目标", "数据收集", "数据预处理", "数据分析及可视化"], "answer": "ABCD", "analysis": "", "sheet": "多选题"}, {"id": 237, "type": "多选题", "question": "大数据4V特性中，多样性指的是", "options": ["数据来源多", "数据类型多", "数据之间关联性强", "数据规模多样"], "answer": "AB", "analysis": "", "sheet": "多选题"}, {"id": 238, "type": "多选题", "question": "在数据科学常见的统计学知识集中趋势中，其常用方法是", "options": ["平均数", "中位数", "最小值", "最大值"], "answer": "AB", "analysis": "", "sheet": "多选题"}, {"id": 239, "type": "多选题", "question": "数据科学的理论基础主要包括", "options": ["统计学", "机器学习", "数据可视化", "领域知识"], "answer": "ABD", "analysis": "", "sheet": "多选题"}, {"id": 240, "type": "多选题", "question": "数据科学有哪些性质", "options": ["有效性", "可用性", "未预料", "可理解"], "answer": "ABCD", "analysis": "", "sheet": "多选题"}, {"id": 241, "type": "多选题", "question": "哪些属于数据可视化的重要作用", "options": ["分析数据", "采集数据", "辅助理解数据", "观测跟踪数据"], "answer": "ACD", "analysis": "", "sheet": "多选题"}, {"id": 242, "type": "多选题", "question": "数据可视化的呈现方式有", "options": ["电子表格", "条形统计图", "扇形统计图", "动态热力图"], "answer": "BCD", "analysis": "", "sheet": "多选题"}, {"id": 243, "type": "多选题", "question": "数据可视化的三要素", "options": ["信息", "设计", "沟通", "数据"], "answer": "ABC", "analysis": "", "sheet": "多选题"}, {"id": 244, "type": "多选题", "question": "数据分析方法包括", "options": ["列表法", "对比法", "作图法", "走势分析法"], "answer": "ABCD", "analysis": "", "sheet": "多选题"}, {"id": 245, "type": "多选题", "question": "数据加工的主要任务是对数据进行", "options": ["传播", "变换", "抽取", "运算"], "answer": "BCD", "analysis": "", "sheet": "多选题"}, {"id": 246, "type": "多选题", "question": "MapReduce与HBase的关系，哪些描述是正确的？", "options": ["两者不可或缺，MapReduce是HBase可以正常运行的保证", "两者不是强关联关系，没有MapReduce，HBase可以正常运行", "MapReduce可以直接访问HBase", "它们之间没有任何关系"], "answer": "BC", "analysis": "", "sheet": "多选题"}, {"id": 247, "type": "多选题", "question": "下面哪个程序不是负责 HDFS 数据存储", "options": ["NameNode", "Jobtracker", "Datanode", "tasktracker"], "answer": "BD", "analysis": "", "sheet": "多选题"}, {"id": 248, "type": "多选题", "question": "MapReduce为了保证任务的正常执行，采用________等多种容错机制。", "options": ["重复执行", "重新开始整个任务", "推测执行", "直接丢弃执行效率低的作业"], "answer": "AC", "analysis": "", "sheet": "多选题"}, {"id": 249, "type": "多选题", "question": "HBase构建二级索引的实现方式有哪些", "options": ["MapReduce", "Coprocessor", "Bloom Filter", "Filter"], "answer": "AB", "analysis": "", "sheet": "多选题"}, {"id": 250, "type": "多选题", "question": "下面哪些是spark比Mapreduce计算快的原因（ ）", "options": ["基于内存的计算", "基于DAG的调度框架", "基于Lineage的容错机制", "基于分布式计算的框架"], "answer": "ABC", "analysis": "", "sheet": "多选题"}, {"id": 251, "type": "多选题", "question": "MapReduce体系结构主要由哪几个部分组成", "options": ["TaskTracker", "Task", "JobTracker", "Client"], "answer": "ABCD", "analysis": "", "sheet": "多选题"}, {"id": 252, "type": "多选题", "question": "对MapReduce的体系结构，以下说法正确的是", "options": ["分布式编程架构", "以数据为中心，更看重吞吐率", "分而治之的思想", "将一个任务分解成多个子任务"], "answer": "ABCD", "analysis": "", "sheet": "多选题"}, {"id": 253, "type": "多选题", "question": "Spark支持哪3种语言", "options": ["golang", "scala", "python", "java"], "answer": "BCD", "analysis": "", "sheet": "多选题"}, {"id": 254, "type": "多选题", "question": "Spark有哪三大特点", "options": ["适用性强", "成本高", "通用性强", "速度快"], "answer": "ACD", "analysis": "", "sheet": "多选题"}, {"id": 255, "type": "多选题", "question": "下列可以用于分类问题的机器学习算法有：", "options": ["决策树", "随机森林", "k近邻", "逻辑回归"], "answer": "ABCD", "analysis": "", "sheet": "多选题"}, {"id": 256, "type": "多选题", "question": "下列既可以用于分类，又可以用于回归的机器学习算法有：", "options": ["k近邻", "逻辑回归", "决策树", "线性回归"], "answer": "AC", "analysis": "", "sheet": "多选题"}, {"id": 257, "type": "多选题", "question": "机器学习应用开发的典型步骤有哪些？", "options": ["数据采集和标记", "数据清洗", "特征选择", "模型选择", "模型训练和测试", "模型性能评估和优化", "模型使用"], "answer": "ABCDEFG", "analysis": "", "sheet": "多选题"}, {"id": 258, "type": "多选题", "question": "以下哪种方法能够防止过拟合（）", "options": ["增加训练次数", "正则化", "数据集扩增", "dropout"], "answer": "BCD", "analysis": "", "sheet": "多选题"}, {"id": 259, "type": "多选题", "question": "关于降维说法正确的是（\t）", "options": ["PA是根据方差这一属性降维的", "降维可以防止模型过拟合", "降维降低了数据集特征的维度", "降维方法有PLA等"], "answer": "ABC", "analysis": "", "sheet": "多选题"}, {"id": 260, "type": "多选题", "question": "下列哪些方法可以用来对高维数据进行降维（ ）", "options": ["主成分分析法", "聚类分析", "小波分析法", "线性判别法"], "answer": "ACD", "analysis": "", "sheet": "多选题"}, {"id": 261, "type": "多选题", "question": "下列关于 PCA 说法正确的是", "options": ["在使用 PCA 之前，我们必须标准化数据", "应该选择具有最大方差的主成分", "应该选择具有最小方差的主成分", "可以使用 PCA 在低维空间中可视化数据"], "answer": "ABD", "analysis": "", "sheet": "多选题"}, {"id": 262, "type": "多选题", "question": "Knn算法的优点包括以下哪项（）", "options": ["精度高", "计算复杂度低", "对异常值不敏感", "无数据输入假定"], "answer": "AD", "analysis": "", "sheet": "多选题"}, {"id": 263, "type": "多选题", "question": "分类模型包括哪些？", "options": ["主成分分析", "lasso回归", "逻辑回归", "决策树"], "answer": "CD", "analysis": "", "sheet": "多选题"}, {"id": 264, "type": "多选题", "question": "回归模型包括哪些？", "options": ["支持向量机（SVM）", "lasso回归", "逻辑回归", "决策树"], "answer": "BD", "analysis": "", "sheet": "多选题"}, {"id": 265, "type": "多选题", "question": "数据驱动的特征选择常用方法有：", "options": ["基于模型选择特征", "迭代删除特征", "迭代增加特征", "相关性"], "answer": "ABCD", "analysis": "", "sheet": "多选题"}, {"id": 266, "type": "多选题", "question": "属于特征选择的优点有（\t）", "options": ["解决模型自身的缺陷", "减少过拟合", "提升模型的性能", "增强模型的泛化能力"], "answer": "BCD", "analysis": "", "sheet": "多选题"}, {"id": 267, "type": "多选题", "question": "属于特征选择的方法有（\t）", "options": ["嵌入法", "包裹式", "过滤法", "随机法"], "answer": "ABC", "analysis": "", "sheet": "多选题"}, {"id": 268, "type": "多选题", "question": "特征选择的主要目的包括以下哪项（）", "options": ["降低数据维度", "提高预测准确度", "增强模型泛化能力", "增强对特征和特征值之间的理解"], "answer": "ABCD", "analysis": "", "sheet": "多选题"}, {"id": 269, "type": "多选题", "question": "以下哪些项是特征选择的方法", "options": ["过滤法", "包装法", "假定法", "嵌入法"], "answer": "ABD", "analysis": "", "sheet": "多选题"}, {"id": 270, "type": "多选题", "question": "下面关于回归的说法，正确的是：", "options": ["自变量X（也就是特征）往往包含多个特征", "回归用于分析自变量和应变量之间的关系", "线性回归是一种经典的回归分析方法", "在回归中，建立应变量关于自变量的函数，应变量是自变量在函数上的映射"], "answer": "ABCD", "analysis": "", "sheet": "多选题"}, {"id": 271, "type": "多选题", "question": "下面关于逻辑回归的说法，正确的是：", "options": ["逻辑回归主要应用于二分类问题", "逻辑回归使用Logistic Function 后得到的数值在-1到1之间", "把逻辑回归应用于多分类问题时，需要使用One vs. Rest方法", "逻辑回归得到的数值可以看作属于类别1的概率"], "answer": "ACD", "analysis": "", "sheet": "多选题"}, {"id": 272, "type": "多选题", "question": "以下关于损失函数说法正确的是（）", "options": ["损失函数可以用于评价模型的拟合效果", "损失函数的选取是固定的", "可以通过损失函数构造优化目标", "线性回归模型常用mse作为损失函数"], "answer": "ACD", "analysis": "", "sheet": "多选题"}, {"id": 273, "type": "多选题", "question": "线性模型的优点有哪些？", "options": ["形式简单，易于建模", "易于理解comprehensibility", "可以引入正则化来降低拟合的风险", "线性回归在变量是非线性关系的时候表现很好"], "answer": "ABC", "analysis": "", "sheet": "多选题"}, {"id": 274, "type": "多选题", "question": "线性回归的两个主要类型是？", "options": ["简单线性回归", "复杂线性回归", "多元线性回归", "多分类线性回归"], "answer": "AC", "analysis": "", "sheet": "多选题"}, {"id": 275, "type": "多选题", "question": "下列哪些假设是我们推导线性回归参数时遵循的", "options": ["X 与 Y 有线性关系（多项式关系）", "模型误差在统计学上是独立的", "误差一般服从 0 均值和固定标准差的正态分布", "X 是非随机且测量没有误差的"], "answer": "ABCD", "analysis": "", "sheet": "多选题"}, {"id": 276, "type": "多选题", "question": "线性模型针对类别不平衡问题有哪些处理方法？", "options": ["再缩放（rescaling）", "欠采样（undersampling）", "过采样（oversampling）", "阈值移动（threshold-moving）"], "answer": "ABCD", "analysis": "", "sheet": "多选题"}, {"id": 277, "type": "多选题", "question": "下面关于决策树的说法，正确的是：", "options": ["决策树有二叉树和多叉树", "建立决策树模型的时候，可能不需要用到数据集中的所有特征来建立决策树节点的分裂规则", "决策树子节点分裂时，选择的是最优的特征进行分裂", "决策树只能用于分类"], "answer": "ABC", "analysis": "", "sheet": "多选题"}, {"id": 278, "type": "多选题", "question": "决策树学习通常包括的步骤有哪些？", "options": ["特征选择", "决策树的生成", "决策树的修剪"], "answer": "ABC", "analysis": "", "sheet": "多选题"}, {"id": 279, "type": "多选题", "question": "解决决策树过拟合的方法有哪些？", "options": ["前剪枝", "后剪枝", "正则化项"], "answer": "ABC", "analysis": "", "sheet": "多选题"}, {"id": 280, "type": "多选题", "question": "下列是svm核函数的是（）", "options": ["多项式核函数", "logistic核函数", "径向基核函数", "sigmoid核函数"], "answer": "ACD", "analysis": "", "sheet": "多选题"}, {"id": 281, "type": "多选题", "question": "sklearn.svm.SVC()的主要参数包括哪些？", "options": ["惩罚系数C", "核函数kernel", "Gamma", "类别权重class_weight"], "answer": "ABCD", "analysis": "", "sheet": "多选题"}, {"id": 282, "type": "多选题", "question": "以下哪层是卷积神经网络的组成部分", "options": ["卷积层", "中间层", "池化层", "全连接层"], "answer": "ACD", "analysis": "", "sheet": "多选题"}, {"id": 283, "type": "多选题", "question": "依据图像的保真度，图像压缩可分为", "options": ["无损压缩", "批量压缩", "有损压缩", "高压"], "answer": "AC", "analysis": "", "sheet": "多选题"}, {"id": 284, "type": "多选题", "question": "图像压缩是建立在图像存在(  )三种冗余基础上", "options": ["编码冗余", "像素间冗余", "心理视觉冗余", "图形冗余"], "answer": "ABC", "analysis": "", "sheet": "多选题"}, {"id": 285, "type": "多选题", "question": "对于彩色图像，通常用以区别颜色的特性是", "options": ["色调", "饱和度", "亮度", "色相"], "answer": "ABC", "analysis": "", "sheet": "多选题"}, {"id": 286, "type": "多选题", "question": "文本语料库的可能特征是什么？", "options": ["文本中词计数", "词的向量标注", "词性标注", "基本依存语法"], "answer": "ABCD", "analysis": "", "sheet": "多选题"}, {"id": 287, "type": "多选题", "question": "下列哪些技术能被用于计算两个词向量之间的距离？", "options": ["词形还原", "欧氏距离", "余弦相似度", "N-grams"], "answer": "BC", "analysis": "", "sheet": "多选题"}, {"id": 288, "type": "多选题", "question": "下列哪项是关键词归一化技术？", "options": ["词干提取", "词性标注", "命名实体识别", "词形还原"], "answer": "AD", "analysis": "", "sheet": "多选题"}, {"id": 289, "type": "多选题", "question": "spark与hadoop的不同点在于()。", "options": ["应用场景不同", "hadoop处理速度更快", "spark处理速度更快", "容错性不同"], "answer": "ACD", "analysis": "", "sheet": "多选题"}, {"id": 290, "type": "多选题", "question": "用于评估回归模型优劣的指标是()。", "options": ["RMSE", "AUC", "MAE", "MSLE"], "answer": "ACD", "analysis": "", "sheet": "多选题"}, {"id": 291, "type": "多选题", "question": "大数据的特征包括()。", "options": ["数据体量大", "数据类型繁多", "数据产生速度快", "数据价值密度低"], "answer": "ABCD", "analysis": "", "sheet": "多选题"}, {"id": 292, "type": "多选题", "question": "下列可以用于聚类问题的机器学习算法有()。", "options": ["决策树", "k-means", "DBSCAN", "逻辑回归"], "answer": "BC", "analysis": "", "sheet": "多选题"}, {"id": 293, "type": "多选题", "question": "造成过拟合现象的原因包括()。", "options": ["训练数据集样本单一，样本不足", "训练数据中噪声干扰过大", "模型过于简单", "模型学习能力差"], "answer": "AB", "analysis": "", "sheet": "多选题"}, {"id": 294, "type": "多选题", "question": "特征选择的方法包括()。", "options": ["过滤式选择", "包裹式选择", "嵌入式选择", "K近邻学习"], "answer": "ABC", "analysis": "", "sheet": "多选题"}, {"id": 295, "type": "多选题", "question": "下列关于SVM说法正确的是()。", "options": ["SVM是一种监督式学习的方法", "支持向量机只能解决二分类问题", "支持向量机可以解决分界线为曲线的分类问题", "支持向量机的核函数将原来的输入空间变换到一个新的特征空间"], "answer": "ACD", "analysis": "", "sheet": "多选题"}, {"id": 296, "type": "多选题", "question": "下列模型中属于监督学习的为()。", "options": ["K-means聚类", "决策树", "SVM", "PCA"], "answer": "BC", "analysis": "", "sheet": "多选题"}, {"id": 297, "type": "多选题", "question": "下面哪些函数可以作为支持向量机的核函数()。", "options": ["多项式函数", "高斯函数", "Sigmoid函数", "拉普拉斯函数"], "answer": "ABCD", "analysis": "", "sheet": "多选题"}, {"id": 298, "type": "多选题", "question": "下列属于集成学习算法的是()。", "options": ["AdaBoost", "随机森林", "平均法", "逻辑回归"], "answer": "AB", "analysis": "", "sheet": "多选题"}, {"id": 299, "type": "多选题", "question": "下列属于时间序列预测算法的是()。", "options": ["朴素贝叶斯", "指数平滑", "Apriori", "ARIMA"], "answer": "BD", "analysis": "", "sheet": "多选题"}, {"id": 300, "type": "多选题", "question": "下列指标哪些是聚类任务的性能度量。", "options": ["Jaccard系数", "FM指数", "Rand指数", "基尼指数"], "answer": "ABC", "analysis": "", "sheet": "多选题"}, {"id": 301, "type": "多选题", "question": "影响基本K-means算法结果的主要因素有()。", "options": ["样本输入顺序", "模式相似性测度", "聚类准则", "初始类中心的选取"], "answer": "ABCD", "analysis": "", "sheet": "多选题"}, {"id": 302, "type": "多选题", "question": "聚类算法中，关于簇相关距离参数说法正确的是()。", "options": ["簇内平均距离，越大越好", "簇内最大距离，越小越好", "簇间最小距离，越大越好", "簇中心距离，越小越好"], "answer": "BC", "analysis": "", "sheet": "多选题"}, {"id": 303, "type": "多选题", "question": "下列模型属于机器学习生成式模型的是()。", "options": ["朴素贝叶斯", "隐马尔科夫模型(HMM)", "马尔科夫随机场(Markov Random Fields)", "深度信念网络(DBN)"], "answer": "ABCD", "analysis": "", "sheet": "多选题"}, {"id": 304, "type": "多选题", "question": "数据挖掘的基本流程包含()。", "options": ["采集、表示与存储", "清洗、集成", "分析、展现", "决策"], "answer": "ABCD", "analysis": "", "sheet": "多选题"}, {"id": 305, "type": "多选题", "question": "支持向量机的核函数有哪些?", "options": ["线性核", "多项式的核", "径向基核", "Sigmoid 核"], "answer": "ABCD", "analysis": "", "sheet": "多选题"}, {"id": 306, "type": "多选题", "question": "通过数据挖掘过程所推倒出的关系和摘要经常被称为", "options": ["模型", "模式", "模范", "模具"], "answer": "AB", "analysis": "", "sheet": "多选题"}, {"id": 307, "type": "多选题", "question": "寻找数据集中的关系是为了寻找精确、方便并且有价值地总结了数据的某一特征的表示，这个过程包括了以下哪些步骤？", "options": ["决定要使用的表示的特征和结构", "决定如何量化和比较不同表示拟合数据的好坏", "选择一个算法过程使评分函数最优", "决定用什么样的数据管理原则以高效地实现算法"], "answer": "ABCD", "analysis": "", "sheet": "多选题"}, {"id": 308, "type": "多选题", "question": "数据挖掘的预测建模任务主要包括哪几大类问题？", "options": ["分类", "回归", "模式发现", "模式匹配"], "answer": "AB", "analysis": "", "sheet": "多选题"}, {"id": 309, "type": "多选题", "question": "数据挖掘算法的组件包括", "options": ["模型或模型结构", "评分函数", "优化和搜索方法", "数据管理策略"], "answer": "ABCD", "analysis": "", "sheet": "多选题"}, {"id": 310, "type": "多选题", "question": "以下哪些学科和数据挖掘有密切联系？", "options": ["统计", "计算机组成原理", "矿产挖掘", "人工智能"], "answer": "AD", "analysis": "", "sheet": "多选题"}, {"id": 311, "type": "多选题", "question": "对于数据挖掘中的原始数据，存在的问题有", "options": ["不一致", "重复", "不完整", "含噪声", "维度高"], "answer": "ABCDE", "analysis": "", "sheet": "多选题"}, {"id": 312, "type": "多选题", "question": "下面属于数据集的一般特性的有", "options": ["连续性", "维度", "稀疏性", "分辨率", "相异性"], "answer": "BCD", "analysis": "", "sheet": "多选题"}, {"id": 313, "type": "多选题", "question": "下面属于维归约常用的线性代数技术的有", "options": ["主成分分析", "特征提取", "奇异值分解", "特征加权", "离散化"], "answer": "AC", "analysis": "", "sheet": "多选题"}, {"id": 314, "type": "多选题", "question": "联机分析处理包括以下哪些基本分析功能？", "options": ["聚类", "切片", "转轴", "切块", "分类"], "answer": "BCD", "analysis": "", "sheet": "多选题"}, {"id": 315, "type": "多选题", "question": "以下属于分类器评价或比较尺度的有", "options": ["预测准确度", "召回率", "模型描述的简洁度", "计算复杂度"], "answer": "ABCD", "analysis": "", "sheet": "多选题"}, {"id": 316, "type": "多选题", "question": "在评价不平衡类问题分类的度量方法有如下几种", "options": ["F1度量", "召回率", "精度", "真正率"], "answer": "ABCD", "analysis": "", "sheet": "多选题"}, {"id": 317, "type": "多选题", "question": "以下属于聚类算法的是", "options": ["K均值", "DBSCAN", "Apriori", "Jarvis-Patrick（JP）"], "answer": "ABD", "analysis": "", "sheet": "多选题"}, {"id": 318, "type": "多选题", "question": "簇有效性的面向相似性的度量包括", "options": ["精度", "Rand统计量", "Jaccard系数", "召回率"], "answer": "BC", "analysis": "", "sheet": "多选题"}, {"id": 319, "type": "多选题", "question": "(   )这些数据特性都是对聚类分析具有很强影响的", "options": ["高维性", "规模", "稀疏性", "噪声和离群点"], "answer": "ABCD", "analysis": "", "sheet": "多选题"}, {"id": 320, "type": "多选题", "question": "在聚类分析当中，（  ）等技术可以处理任意形状的簇。", "options": ["MIN（单链）", "MAX（全链）", "组平均", "Chameleon"], "answer": "AD", "analysis": "", "sheet": "多选题"}, {"id": 321, "type": "多选题", "question": "为什么RNN（递归神经网络）被用于机器翻译，比如说将英语翻译成法语？", "options": ["它可以训练成一个有监督的学习问题", "它比卷积神经网络（CNN）更强大", "当输入/输出是一个序列（例如，一个单词序列）时适用", "RNN表示 想法->代码->实验->想法->... 的循环过程"], "answer": "AC", "analysis": "", "sheet": "多选题"}, {"id": 322, "type": "多选题", "question": "你正在为苹果，香蕉和橘子制作分类器。 假设您的分类器在训练集上有0.5％的错误，以及开发集上有7％的错误。 以下哪项尝试是有希望改善你的分类器的分类效果的？", "options": ["增大正则化参数", "减小正则化参数", "获取更多训练数据", "用更大的神经网络"], "answer": "AC", "analysis": "", "sheet": "多选题"}, {"id": 323, "type": "多选题", "question": "RDD 作为 Spark 最核心的对象，具有以下哪些特点？", "options": ["只读", "分区", "容错", "高效"], "answer": "ABCD", "analysis": "", "sheet": "多选题"}, {"id": 324, "type": "多选题", "question": "下面关于连续型随机变量以及连续型概率密度函数的说法，正确的有", "options": ["“一个客服一天可能接听到多少个电话”是一个连续型随机变量", "正态分布是一种连续型随机变量的概率分布", "可以使用概率密度函数来描述连续型随机变量的概率分布", "连续型概率密度函数曲线下方的面积之和为1"], "answer": "BCD", "analysis": "", "sheet": "多选题"}, {"id": 325, "type": "多选题", "question": "RDD有哪些缺陷", "options": ["不支持细粒度的写和更新操作（如网络爬虫）", "基于内存的计算", "拥有schema信息", "不支持增量迭代计算"], "answer": "AD", "analysis": "", "sheet": "多选题"}, {"id": 326, "type": "多选题", "question": "scikit-learn包含的聚类方法有？", "options": ["K-Means", "Affinity propagation", "Spectral clustering", "logistics"], "answer": "ABC", "analysis": "", "sheet": "多选题"}, {"id": 327, "type": "多选题", "question": "如何在监督式学习中使用聚类算法", "options": ["首先，可以创建聚类，然后分别在不同的集群上应用监督式学习算法", "在应用监督式学习算法之前，可以将其类别 ID 作为特征空间中的一个额外的特征", "在应用监督式学习之前，不能创建聚类", "在应用监督式学习算法之前，不能将其类别 ID 作为特征空间中的一个额外的特征"], "answer": "AB", "analysis": "", "sheet": "多选题"}, {"id": 328, "type": "多选题", "question": "Spark RDD的依赖机制包括", "options": ["宽依赖", "深度依赖", "广度依赖", "窄依赖"], "answer": "AD", "analysis": "", "sheet": "多选题"}, {"id": 329, "type": "多选题", "question": "以下关于case class描述对的是", "options": ["默认情况下可对其属性进行修改。", "在模式匹配时会进行解构操作。", "两个case class进行比较时进行全等比较，而非按是否引用同一个对象进行比较。", "相比于class而言更简洁的实例化过程(不需要使用new操作符)及其它操作语法。"], "answer": "BCD", "analysis": "", "sheet": "多选题"}, {"id": 330, "type": "多选题", "question": "关于数据库的说法，正确的是：", "options": ["主流的非关系型数据库有MongoDB、Redis、NoSQL等", "关系型数据库MySQL、Oracle、SQLServer、SQLite等可以通用SQL语言", "除了MySQL之外，主流的关系型数据库还有Oracle、SQLServer、SQLite等", "非关系型数据库MongoDB具有一套不同于SQL的查询语言"], "answer": "BCD", "analysis": "", "sheet": "多选题"}, {"id": 331, "type": "多选题", "question": "常用的灰度内插法有", "options": ["最近邻元法", "双线性内插法", "(双)三次内插法", "单次插入发"], "answer": "ABC", "analysis": "", "sheet": "多选题"}, {"id": 332, "type": "多选题", "question": "图像数字化过程包括三个步骤", "options": ["采样", "量化", "定位", "均衡", "扫描"], "answer": "ABE", "analysis": "", "sheet": "多选题"}, {"id": 333, "type": "多选题", "question": "下面哪些选项正确描述了HBase的特性？", "options": ["高可靠性", "高性能", "面向列", "可伸缩"], "answer": "ABCD", "analysis": "", "sheet": "多选题"}, {"id": 334, "type": "多选题", "question": "Scikit-learn包括哪些模型？", "options": ["分类", "回归", "聚类", "预测"], "answer": "ABC", "analysis": "", "sheet": "多选题"}, {"id": 335, "type": "多选题", "question": "直方图修正法包括( )两种方法;", "options": ["直方图规划", "直方图均衡", "直方图规定化", "直方图方差"], "answer": "BC", "analysis": "", "sheet": "多选题"}, {"id": 336, "type": "多选题", "question": "下面对HBase的描述哪些是正确的？", "options": ["不是开源的", "是面向列的", "是分布式的", "是一种NoSQL数据库"], "answer": "BCD", "analysis": "", "sheet": "多选题"}, {"id": 337, "type": "多选题", "question": "flask网站程序的结构为（\t）。", "options": ["html模板", "templates文件夹", "static", "主程序"], "answer": "ABCD", "analysis": "", "sheet": "多选题"}, {"id": 338, "type": "多选题", "question": "下面对于HTML说法正确的有:", "options": ["在写html文件时需要注意特殊字符的问题，html的特殊字符是通过“&（加上一串代表字符的字母）”来输入的，比如想要输入“<”需要输入“&<”", "HTML由标签组成，由<html>开始，</html>结束", "HTML常用的标签包括超链接、图片、列表、表格、表单等", "标签可以具有属性，在<img src = ”logo.jpg”  alt =”logo”/>中，alt是标签img的属性"], "answer": "BCD", "analysis": "", "sheet": "多选题"}, {"id": 339, "type": "多选题", "question": "以下方法不需要目标向量的是（\t）", "options": ["特征选择嵌入法", "无监督学习", "监督学习", "特征选择过滤法"], "answer": "BD", "analysis": "", "sheet": "多选题"}, {"id": 340, "type": "多选题", "question": "numpy中常用的方法包括：", "options": ["zeros()", "ones()", "empty()", "eye()"], "answer": "ABCD", "analysis": "", "sheet": "多选题"}, {"id": 341, "type": "多选题", "question": "Cloudera 提供哪几种安装 CDH 的方法", "options": ["Cloudera manager", "Tarball", "Yum", "Rpm"], "answer": "ABCD", "analysis": "", "sheet": "多选题"}, {"id": 342, "type": "多选题", "question": "下面对于处理缺失数据的方法，正确的有（）", "options": ["缺失数据的处理必须遵循固定的标准和步骤，防止关键信息丢失", "一种方法是忽略有缺失数据的记录，但对于观测值较少的数据容易造成关键数据丢失", "一种方法是直接把缺失值标记为未知", "可以使用平均值或最常出现的值等不同的方法填充数据"], "answer": "BD", "analysis": "", "sheet": "多选题"}, {"id": 343, "type": "多选题", "question": "关于ARMA, AR, MA模型的功率谱，下列说法错误的是（）", "options": ["AR模型在零点接近单位圆时，AR谱是一个尖峰", "ARMA谱既有尖峰又有深谷", "MA模型在极点接近单位圆时，MA谱是一个深谷", "MA模型是同一个全通滤波器产生的"], "answer": "ACD", "analysis": "", "sheet": "多选题"}, {"id": 344, "type": "多选题", "question": "一个基本的数字图像处理系统由( ) 5个模块组成", "options": ["图像输入", "图像存储", "图像输出", "图像处理和分析", "图像压缩", "图像层叠", "图像通信"], "answer": "ABCDG", "analysis": "", "sheet": "多选题"}, {"id": 345, "type": "多选题", "question": "python的优点有（\t）。", "options": ["语言可解释性强", "变量不用预定义类型", "变量类型固定", "数据结构功能强大"], "answer": "ABD", "analysis": "", "sheet": "多选题"}, {"id": 346, "type": "多选题", "question": "以下说法不正确的是（）", "options": ["ounter方法可以使用在所有迭代的对象上", "get方法只能使用在类似列表的数据类型上", "ounter方法可以应对数据量更大的的情况，因此应用范围更广", "get方法可以使用在所有迭代的对象上"], "answer": "ABC", "analysis": "", "sheet": "多选题"}, {"id": 347, "type": "多选题", "question": "下列选项中，是CouchDB的复制中的特点是", "options": ["使用优先列表", "复制过程是逐步进行", "允许分区复制", "支持智能文档模式"], "answer": "BCD", "analysis": "", "sheet": "多选题"}, {"id": 348, "type": "多选题", "question": "关于服务器-客户端型数据库和文件型数据库的区别，以下哪些说法是正确的：", "options": ["关于前者，数据库是安装在数据库服务器上的，客户端需要通过网络连接来进行访问", "文件型数据库是存储在本地的，一些浏览器会倾向于使用这一类的数据库存储一些用户记录", "关于前者，任何一个机器都可以通过IP进行对数据库服务器的访问，但是会受到账户密码的权限限制", "前者相对后者而言，更轻量级"], "answer": "ABC", "analysis": "", "sheet": "多选题"}, {"id": 349, "type": "多选题", "question": "以下关于API爬虫哪些说法是正确的：", "options": ["基于API返回的结果通常会比较干净", "基于API的爬取能够覆盖网站所有信息", "使用爬虫获取豆瓣电影评分任务中，操作步骤一般是确定爬取链接、读取链接指向内容、抽取关键元素", "基于API的爬虫爬取的好处是没有次数的限制"], "answer": "AC", "analysis": "", "sheet": "多选题"}, {"id": 350, "type": "多选题", "question": "关于HBase二级索引的描述，哪些是正确的？", "options": ["核心是倒排表", "二级索引概念是对应Rowkey这个“一级”索引", "二级索引使用平衡二叉树", "二级索引使用LSM结构"], "answer": "AB", "analysis": "", "sheet": "多选题"}, {"id": 351, "type": "多选题", "question": "SQL语言允许使用通配符进行字符串匹配的操作,其中‘%’可以表示", "options": ["零个字符", "1个字符", "多个字符"], "answer": "ABC", "analysis": "", "sheet": "多选题"}, {"id": 352, "type": "多选题", "question": "下面哪些语句是DML（数据库操作语言） （ ）", "options": ["SELECT", "INSERT", "DROP", "CREATE"], "answer": "AB", "analysis": "", "sheet": "多选题"}, {"id": 353, "type": "多选题", "question": "Python导入os模块，使用模块中的那几个方法可以文件删除", "options": ["remove(f)", "rmdir(dir)", "removedirs(dir)", "mvdirs()"], "answer": "ABC", "analysis": "", "sheet": "多选题"}, {"id": 354, "type": "多选题", "question": "Svm适用于以下哪种数据集 （）", "options": ["线性可分的数据集", "含有很多噪声和重叠的数据", "经过清洗较为干净的数据", "以上数据都适用"], "answer": "AB", "analysis": "", "sheet": "多选题"}, {"id": 355, "type": "多选题", "question": "关于 Python 语言的特点，以下选项中描述正确的是", "options": ["Python 语言是非开源语言", "Python 语言是跨平台语言", "Python 语言是多模型语言", "Python 语言是脚本语言"], "answer": "BCD", "analysis": "", "sheet": "多选题"}, {"id": 356, "type": "多选题", "question": "pandas有那两个数据结构？", "options": ["Series", "Dataframe", "array", "list"], "answer": "AB", "analysis": "", "sheet": "多选题"}, {"id": 357, "type": "多选题", "question": "以下影响聚类算法结果的主要因素有", "options": ["样本质量", "分类准则", "特征选取", "模式相似性测度"], "answer": "ABCD", "analysis": "", "sheet": "多选题"}, {"id": 358, "type": "多选题", "question": "对于Scala中混入了特质的对象，关于其在构造时构造器执行顺序的描述正确的是", "options": ["首先调用超类的构造器。", "特质构造器在超类构造器之后、类构造器之前执行。所有特质构造完毕，子类被构造。", "特质由右到左被构造。如果多个特质共有一个父特质，而那个父特质已经被构造，则不会再次构造。", "每个特质中，父特质先被构造。"], "answer": "ABD", "analysis": "", "sheet": "多选题"}, {"id": 359, "type": "判断题", "question": "数据就是就是通过观察、检测或计算得出的数值，是对客观事物的逻辑归纳，用于表示客观事物的未经加工的的原始素材。数据有很多种，最简单的就是数字，也可以是文字、图像、声音、符号、视频等等，是组成信息系统的最基本要素。", "options": ["对", "错"], "answer": "A", "analysis": "", "sheet": "判断题"}, {"id": 360, "type": "判断题", "question": "大数据技术和云计算技术是两门完全不相关的技术。", "options": ["对", "错"], "answer": "B", "analysis": "", "sheet": "判断题"}, {"id": 361, "type": "判断题", "question": "大数据是通过传统数据库技术和数据处理工具不能处理的庞大而复杂的数据集合。", "options": ["对", "错"], "answer": "A", "analysis": "", "sheet": "判断题"}, {"id": 362, "type": "判断题", "question": "大数据的最显著特征是数据类型多样", "options": ["对", "错"], "answer": "B", "analysis": "", "sheet": "判断题"}, {"id": 363, "type": "判断题", "question": "数据可视化可以便于人们对数据的理解。", "options": ["对", "错"], "answer": "A", "analysis": "", "sheet": "判断题"}, {"id": 364, "type": "判断题", "question": "特征工程直接用相关性计算即可", "options": ["对", "错"], "answer": "B", "analysis": "", "sheet": "判断题"}, {"id": 365, "type": "判断题", "question": "相关性计算为不相关就可以数据分析直接不考虑该字段", "options": ["对", "错"], "answer": "B", "analysis": "", "sheet": "判断题"}, {"id": 366, "type": "判断题", "question": "一张RGB彩色图像可以看作3维数组.", "options": ["对", "错"], "answer": "A", "analysis": "", "sheet": "判断题"}, {"id": 367, "type": "判断题", "question": "将map的输出作为reduce的输入的过程就是shuffle", "options": ["对", "错"], "answer": "A", "analysis": "", "sheet": "判断题"}, {"id": 368, "type": "判断题", "question": "shuffle是MapReduce的核心", "options": ["对", "错"], "answer": "A", "analysis": "", "sheet": "判断题"}, {"id": 369, "type": "判断题", "question": "MapReduce没有容错机制", "options": ["对", "错"], "answer": "B", "analysis": "", "sheet": "判断题"}, {"id": 370, "type": "判断题", "question": "MapReduce 计数器（Counter）为我们提供一个窗口，用于观察 MapReduce Job 运行期的各种细节数据。", "options": ["对", "错"], "answer": "A", "analysis": "", "sheet": "判断题"}, {"id": 371, "type": "判断题", "question": "通过将Map调用的输入数据自动分割为M个数据片段的集合，Map调用被分布到多台机器上执行。", "options": ["对", "错"], "answer": "A", "analysis": "", "sheet": "判断题"}, {"id": 372, "type": "判断题", "question": "在执行一个MapReduce操作时，可能会存在一些落后者拉长整个任务的完成时间。", "options": ["对", "错"], "answer": "A", "analysis": "", "sheet": "判断题"}, {"id": 373, "type": "判断题", "question": "HDFS集群开始启动时，其处于安全模式，可以进行读操作，不能进行写操作。", "options": ["对", "错"], "answer": "A", "analysis": "", "sheet": "判断题"}, {"id": 374, "type": "判断题", "question": "HDFS是分布式文件系统，其命名空间包括块、目录和文件。", "options": ["对", "错"], "answer": "A", "analysis": "", "sheet": "判断题"}, {"id": 375, "type": "判断题", "question": "YARN的基本思想是将JobTracker的两个主要功能（资源管理和作业调度/监控）分离", "options": ["对", "错"], "answer": "A", "analysis": "", "sheet": "判断题"}, {"id": 376, "type": "判断题", "question": "MapReduce设计的一个理念就是“计算向数据靠拢”，而不是“数据向计算靠拢”，因为，移动数据需要大量的网络传输开销。", "options": ["对", "错"], "answer": "A", "analysis": "", "sheet": "判断题"}, {"id": 377, "type": "判断题", "question": "在Hadoop中每个应用程序被表示成一个作业，每个作业又被分成多个任务，JobTracker的负责作业的分解、状态监控以及资源管理。", "options": ["对", "错"], "answer": "A", "analysis": "", "sheet": "判断题"}, {"id": 378, "type": "判断题", "question": "MapReduce 的 input split 一定是一个 block。", "options": ["对", "错"], "answer": "B", "analysis": "", "sheet": "判断题"}, {"id": 379, "type": "判断题", "question": "链式MapReduce计算中，对任意一个MapReduce作业，Map和Reduce阶段可以有无限个Mapper，但Reducer只能有一个。", "options": ["对", "错"], "answer": "B", "analysis": "", "sheet": "判断题"}, {"id": 380, "type": "判断题", "question": "MapReduce计算过程中，相同的key默认会被发送到同一个reduce task处理。", "options": ["对", "错"], "answer": "A", "analysis": "", "sheet": "判断题"}, {"id": 381, "type": "判断题", "question": "HBase依赖MapReduce提供强大的计算能力", "options": ["对", "错"], "answer": "A", "analysis": "", "sheet": "判断题"}, {"id": 382, "type": "判断题", "question": "MapReduce模型的核心是Map和Reduce函数,二者都是由应用程序开发者负责具体实现的。", "options": ["对", "错"], "answer": "A", "analysis": "", "sheet": "判断题"}, {"id": 383, "type": "判断题", "question": "岭回归和最小二乘法的算法复杂度是相同的。", "options": ["对", "错"], "answer": "A", "analysis": "", "sheet": "判断题"}, {"id": 384, "type": "判断题", "question": "机器学习模型的精准度越高，则模型的性能越好", "options": ["对", "错"], "answer": "B", "analysis": "", "sheet": "判断题"}, {"id": 385, "type": "判断题", "question": "把数据集分成训练数据集和测试数据集是为了确保测试的准确性。", "options": ["对", "错"], "answer": "A", "analysis": "", "sheet": "判断题"}, {"id": 386, "type": "判断题", "question": "降维可以防止模型过拟合", "options": ["对", "错"], "answer": "A", "analysis": "", "sheet": "判断题"}, {"id": 387, "type": "判断题", "question": "PCA是一种无监督学习的降维方式", "options": ["对", "错"], "answer": "A", "analysis": "", "sheet": "判断题"}, {"id": 388, "type": "判断题", "question": "k近邻可以用于分类，但是不能用于回归", "options": ["对", "错"], "answer": "B", "analysis": "", "sheet": "判断题"}, {"id": 389, "type": "判断题", "question": "PCA是一个无监督的特征抽取方法，而LDA是一个有监督的方法。", "options": ["对", "错"], "answer": "A", "analysis": "", "sheet": "判断题"}, {"id": 390, "type": "判断题", "question": "特征集合X中可能包含很多冗余或者跟预测目标y无关的特征，所以需要进行特征选择", "options": ["对", "错"], "answer": "A", "analysis": "", "sheet": "判断题"}, {"id": 391, "type": "判断题", "question": "皮尔逊相关系数可以用于指导特征选择", "options": ["对", "错"], "answer": "A", "analysis": "", "sheet": "判断题"}, {"id": 392, "type": "判断题", "question": "特征维度数可以用于指导特征选择", "options": ["对", "错"], "answer": "B", "analysis": "", "sheet": "判断题"}, {"id": 393, "type": "判断题", "question": "同时使用 L1 范数和 L2 范数，即可避免过拟合，同时也实现了降维，并筛选出相应的特征", "options": ["对", "错"], "answer": "A", "analysis": "", "sheet": "判断题"}, {"id": 394, "type": "判断题", "question": "假如你在训练一个线性回归模型,如果数据量较少，容易发生过拟合", "options": ["对", "错"], "answer": "A", "analysis": "", "sheet": "判断题"}, {"id": 395, "type": "判断题", "question": "假如你在训练一个线性回归模型,如果假设空间较小，容易发生过拟合", "options": ["对", "错"], "answer": "B", "analysis": "", "sheet": "判断题"}, {"id": 396, "type": "判断题", "question": "scikit-learn 中的LogisticRegression 类可以实现对多分类问题的预测。", "options": ["对", "错"], "answer": "A", "analysis": "", "sheet": "判断题"}, {"id": 397, "type": "判断题", "question": "逻辑回归（logistic regression）是一种广义的线性回归分析模型，常用于数据挖掘，是二分类问题最常用的一种方法。", "options": ["对", "错"], "answer": "A", "analysis": "", "sheet": "判断题"}, {"id": 398, "type": "判断题", "question": "线性判别分析给定训练样例集，设法将样例投影到一条直线上，使得同样的样例点尽可能接近，异类投影点尽可能远离；在对新的样本点进行分类的时候，同样将其投影到这条直线上，根据投影点的位置来确定样本的类别。", "options": ["对", "错"], "answer": "A", "analysis": "", "sheet": "判断题"}, {"id": 399, "type": "判断题", "question": "决策树可以处理连续值的特征", "options": ["对", "错"], "answer": "A", "analysis": "", "sheet": "判断题"}, {"id": 400, "type": "判断题", "question": "决策树是一种基于树形结构的预测模型，每一个树形分叉代表一个分类条件，叶子节点代表最终的分类结果，其优点在于易于实现，决策时间短，并且适合处理非数值型数据。", "options": ["对", "错"], "answer": "A", "analysis": "", "sheet": "判断题"}, {"id": 401, "type": "判断题", "question": "信息增益表示得知特征A的信息而使得类Y的信息不确定性减少的程度", "options": ["对", "错"], "answer": "A", "analysis": "", "sheet": "判断题"}, {"id": 402, "type": "判断题", "question": "基尼指数Gini(D)表示集合D的不确定性，基尼指数Gini(D,A)表示经A=a分割后集合D的不确定性,基尼指数值越大，样本集合的不确定性也就越大,这一点与熵相似。", "options": ["对", "错"], "answer": "A", "analysis": "", "sheet": "判断题"}, {"id": 403, "type": "判断题", "question": "后剪枝是设置阈值，当信息熵等不纯性度量的指标低于设定值就停止该分支增长。", "options": ["对", "错"], "answer": "B", "analysis": "", "sheet": "判断题"}, {"id": 404, "type": "判断题", "question": "后剪枝策略是完全构建决策树后自底向上剪去不纯度低于设定值的子树。", "options": ["对", "错"], "answer": "A", "analysis": "", "sheet": "判断题"}, {"id": 405, "type": "判断题", "question": "相比其他学习模型，决策树在模型描述上有巨大的优势。推断逻辑直接，方便模型可视化。", "options": ["对", "错"], "answer": "A", "analysis": "", "sheet": "判断题"}, {"id": 406, "type": "判断题", "question": "SVM对噪声（如来自其他分部的噪声样本）具备鲁棒性", "options": ["对", "错"], "answer": "B", "analysis": "", "sheet": "判断题"}, {"id": 407, "type": "判断题", "question": "SVM核函数中高斯径向基核函数rbf应用最广。", "options": ["对", "错"], "answer": "A", "analysis": "", "sheet": "判断题"}, {"id": 408, "type": "判断题", "question": "卷积神经网络的输入层不可以处理多维数据", "options": ["对", "错"], "answer": "B", "analysis": "", "sheet": "判断题"}, {"id": 409, "type": "判断题", "question": "长短时记忆网络成功的解决了原始循环神经网络的缺陷，成为当前最流行的RNN", "options": ["对", "错"], "answer": "A", "analysis": "", "sheet": "判断题"}, {"id": 410, "type": "判断题", "question": "RNN对具有序列特性的数据非常有效，它能挖掘数据中的时序信息以及语义信息", "options": ["对", "错"], "answer": "A", "analysis": "", "sheet": "判断题"}, {"id": 411, "type": "判断题", "question": "卷积神经网络中输出层的上游通常是隐含层", "options": ["对", "错"], "answer": "A", "analysis": "", "sheet": "判断题"}, {"id": 412, "type": "判断题", "question": "卷积神经网络中的全连接层等价于传统前馈神经网络中的隐含层", "options": ["对", "错"], "answer": "A", "analysis": "", "sheet": "判断题"}, {"id": 413, "type": "判断题", "question": "卷积层的功能是对输入数据进行特征提取", "options": ["对", "错"], "answer": "A", "analysis": "", "sheet": "判断题"}, {"id": 414, "type": "判断题", "question": "卷积神经网络（Convolutional Neural Network，CNN）是一种前馈神经网络", "options": ["对", "错"], "answer": "A", "analysis": "", "sheet": "判断题"}, {"id": 415, "type": "判断题", "question": "均值平滑滤波器可用于锐化图像边缘", "options": ["对", "错"], "answer": "B", "analysis": "", "sheet": "判断题"}, {"id": 416, "type": "判断题", "question": "高频加强滤波器可以有效增强图像边缘和灰度平滑区的对比度", "options": ["对", "错"], "answer": "A", "analysis": "", "sheet": "判断题"}, {"id": 417, "type": "判断题", "question": "图像取反操作适用于增强图像主体灰度偏亮的图像", "options": ["对", "错"], "answer": "B", "analysis": "", "sheet": "判断题"}, {"id": 418, "type": "判断题", "question": "彩色图像增强时采用RGB模型进行直方图均衡化可以在不改变图像颜色的基础上对图像的亮度进行对比度增强", "options": ["对", "错"], "answer": "B", "analysis": "", "sheet": "判断题"}, {"id": 419, "type": "判断题", "question": "变换编码常用于有损压缩", "options": ["对", "错"], "answer": "A", "analysis": "", "sheet": "判断题"}, {"id": 420, "type": "判断题", "question": "同态滤波器可以同时实现动态范围压缩和对比度增强", "options": ["对", "错"], "answer": "A", "analysis": "", "sheet": "判断题"}, {"id": 421, "type": "判断题", "question": "当计算机显示器显示的颜色偏蓝时，提高红色和绿色分量可以对颜色进行校正", "options": ["对", "错"], "answer": "A", "analysis": "", "sheet": "判断题"}, {"id": 422, "type": "判断题", "question": "TF-IDF（term frequency–inverse document frequency）是一种用于信息检索与数据挖掘的常用加权技术", "options": ["对", "错"], "answer": "A", "analysis": "", "sheet": "判断题"}, {"id": 423, "type": "判断题", "question": "jieba是中文分词工具", "options": ["对", "错"], "answer": "A", "analysis": "", "sheet": "判断题"}, {"id": 424, "type": "判断题", "question": "TF-IDF帮你建立文档中最重要的词", "options": ["对", "错"], "answer": "A", "analysis": "", "sheet": "判断题"}, {"id": 425, "type": "判断题", "question": "在给到任何神经网络之前，Tokens都会被转换成数字", "options": ["对", "错"], "answer": "A", "analysis": "", "sheet": "判断题"}, {"id": 426, "type": "判断题", "question": "将句子或段落转换为tokens的过程称为词干提取（Stemming）", "options": ["对", "错"], "answer": "B", "analysis": "", "sheet": "判断题"}, {"id": 427, "type": "判断题", "question": "训练CNN时，可以对输入进行旋转、平移、缩放等预处理提高模型泛化能力。这么说是对，还是不对？", "options": ["对", "错"], "answer": "A", "analysis": "", "sheet": "判断题"}, {"id": 428, "type": "判断题", "question": "人口数据集包含不同城市人口、人均GDP、经济增长的统计数据，这是“非结构化”数据的一个例子，因为它包含来自不同来源的数据。", "options": ["对", "错"], "answer": "B", "analysis": "", "sheet": "判断题"}, {"id": 429, "type": "判断题", "question": "由于Hive的数据存储在HDFS中，所以可以保证数据的高容错、高可靠。", "options": ["对", "错"], "answer": "A", "analysis": "", "sheet": "判断题"}, {"id": 430, "type": "判断题", "question": "Hadoop集群最主要的瓶颈是集群的算力问题。", "options": ["对", "错"], "answer": "B", "analysis": "", "sheet": "判断题"}, {"id": 431, "type": "判断题", "question": "列表字符串排序所用函数为sorted、reversed，输出的为正序或反序的列表。", "options": ["对", "错"], "answer": "B", "analysis": "", "sheet": "判断题"}, {"id": 432, "type": "判断题", "question": "在数据预处理过程中，针对缺失值的填充，如果数据集是非正态分布一般是采用均值填充，正态分布一般是采用中位数或众数填充较为合理。", "options": ["对", "错"], "answer": "B", "analysis": "", "sheet": "判断题"}, {"id": 433, "type": "判断题", "question": "对于给定天气信息数据集，已知空气的温度、湿度、气压、是否降雨以及pm2.5指数，需要建立一个回归模型预测pm2.5指数，这属于无监督学习。", "options": ["对", "错"], "answer": "B", "analysis": "", "sheet": "判断题"}, {"id": 434, "type": "判断题", "question": "统计不同城市人口、人均GDP、经济增长的人口统计数据集是“非结构化”数据的一个例子，因为它包含来自不同来源的数据。", "options": ["对", "错"], "answer": "B", "analysis": "", "sheet": "判断题"}, {"id": 435, "type": "判断题", "question": "从给定的特征集合中选择出相关特征子集的过程，称为“特征选择”。", "options": ["对", "错"], "answer": "A", "analysis": "", "sheet": "判断题"}, {"id": 436, "type": "判断题", "question": "在高维情况下出现的数据样本稀疏、距离计算困难的问题，是所有机器学习方法共同面临的严重障碍，被称为“维度灾难”。", "options": ["对", "错"], "answer": "A", "analysis": "", "sheet": "判断题"}, {"id": 437, "type": "判断题", "question": "K近邻算法采用的是“懒惰学习”法，最近邻分类器的泛化错误率不超过贝叶斯最优分类器的错误率的两倍。", "options": ["对", "错"], "answer": "A", "analysis": "", "sheet": "判断题"}, {"id": 438, "type": "判断题", "question": "PCA是有监督学习。", "options": ["对", "错"], "answer": "B", "analysis": "", "sheet": "判断题"}, {"id": 439, "type": "判断题", "question": "应用ID3算法构造决策树的核心是在决策树各个节点上应用信息增益为准则选择特征，递归构建决策树。", "options": ["对", "错"], "answer": "A", "analysis": "", "sheet": "判断题"}, {"id": 440, "type": "判断题", "question": "支持向量机只能解决线性可分问题。", "options": ["对", "错"], "answer": "B", "analysis": "", "sheet": "判断题"}, {"id": 441, "type": "判断题", "question": "朴素贝叶斯法是基于贝叶斯定理与特征条件独立假设的分类方法。", "options": ["对", "错"], "answer": "A", "analysis": "", "sheet": "判断题"}, {"id": 442, "type": "判断题", "question": "EM算法指期望极小算法。", "options": ["对", "错"], "answer": "B", "analysis": "", "sheet": "判断题"}, {"id": 443, "type": "判断题", "question": "AdaBoost算法采用加权多数表决的方法组合基础分类器 。", "options": ["对", "错"], "answer": "A", "analysis": "", "sheet": "判断题"}, {"id": 444, "type": "判断题", "question": "K-Means算法不需要提前指定类别数，即不需要提前指定k的值。", "options": ["对", "错"], "answer": "B", "analysis": "", "sheet": "判断题"}, {"id": 445, "type": "判断题", "question": "聚类分析属于无监督学习。", "options": ["对", "错"], "answer": "A", "analysis": "", "sheet": "判断题"}, {"id": 446, "type": "判断题", "question": "神经网络的更深层通常比前面的层计算更复杂的输入特征。", "options": ["对", "错"], "answer": "A", "analysis": "", "sheet": "判断题"}, {"id": 447, "type": "判断题", "question": "支持向量机学习的基本思想是求解能够正确划分训练数据集并且几何间隔最大的分离超平面。", "options": ["对", "错"], "answer": "A", "analysis": "", "sheet": "判断题"}, {"id": 448, "type": "判断题", "question": "给定n个数据点，如果其中一半用于训练，另一半用于测试，则训练误差和测试误差之间的差别会随着n的增加而减小。", "options": ["对", "错"], "answer": "A", "analysis": "", "sheet": "判断题"}, {"id": 449, "type": "判断题", "question": "隐马尔可夫模型是结构最简单的动态贝叶斯网，主要用于时序建模，在语音识别等领域应用广泛。", "options": ["对", "错"], "answer": "A", "analysis": "", "sheet": "判断题"}, {"id": 450, "type": "判断题", "question": "中值滤波是指将当前像元的窗口（或邻域）中所有像元灰度由小到大进行排序，中间值作为当前像元的输出值。", "options": ["对", "错"], "answer": "A", "analysis": "", "sheet": "判断题"}, {"id": 451, "type": "判断题", "question": "神经网络的学习过程不需要进行反向传播。", "options": ["对", "错"], "answer": "B", "analysis": "", "sheet": "判断题"}, {"id": 452, "type": "判断题", "question": "感知机只有输出层神经元进行激活函数处理，即只有一层功能神经元。", "options": ["对", "错"], "answer": "A", "analysis": "", "sheet": "判断题"}, {"id": 453, "type": "判断题", "question": "k-means属于无监督学习。", "options": ["对", "错"], "answer": "A", "analysis": "", "sheet": "判断题"}, {"id": 454, "type": "判断题", "question": "K-Means算法中的质心必须是数据集中存在的数据。", "options": ["对", "错"], "answer": "B", "analysis": "", "sheet": "判断题"}, {"id": 455, "type": "判断题", "question": "若添加了一个不重要的特征，可能增加了模型均方误差", "options": ["对", "错"], "answer": "A", "analysis": "", "sheet": "判断题"}, {"id": 456, "type": "判断题", "question": "静态方法不需要关键字self", "options": ["对", "错"], "answer": "A", "analysis": "", "sheet": "判断题"}, {"id": 457, "type": "判断题", "question": "对于生成器对象x = (3 for i in range(5))，连续两次执行list(x)的结果是一样的。", "options": ["对", "错"], "answer": "B", "analysis": "", "sheet": "判断题"}, {"id": 458, "type": "判断题", "question": "Hadoop 默认调度器策略为 FIFO", "options": ["对", "错"], "answer": "A", "analysis": "", "sheet": "判断题"}, {"id": 459, "type": "判断题", "question": "scipy.linalg.inv()是 计算矩阵的逆矩阵:", "options": ["对", "错"], "answer": "A", "analysis": "", "sheet": "判断题"}, {"id": 460, "type": "判断题", "question": "DataNode 首次加入 cluster 的时候，如果 log 中报告不兼容文件版本，那需要 NameNode执行“Hadoop namenode -format”操作格式化磁盘。", "options": ["对", "错"], "answer": "B", "analysis": "", "sheet": "判断题"}, {"id": 461, "type": "判断题", "question": "数组a按行的方差：np.var(a, axis=1)", "options": ["对", "错"], "answer": "A", "analysis": "", "sheet": "判断题"}, {"id": 462, "type": "判断题", "question": "每个 map 槽就是一个线程。", "options": ["对", "错"], "answer": "B", "analysis": "", "sheet": "判断题"}, {"id": 463, "type": "判断题", "question": "HBase是分布式列式存储系统，记录按列族集中存放", "options": ["对", "错"], "answer": "A", "analysis": "", "sheet": "判断题"}, {"id": 464, "type": "判断题", "question": "stats.mode()计算数据的平均值", "options": ["对", "错"], "answer": "B", "analysis": "", "sheet": "判断题"}, {"id": 465, "type": "判断题", "question": "HBase对于空（NULL）的列，不需要占用存储空间。", "options": ["对", "错"], "answer": "A", "analysis": "", "sheet": "判断题"}, {"id": 466, "type": "判断题", "question": "辅助构造器的参数可以是任意多个", "options": ["对", "错"], "answer": "A", "analysis": "", "sheet": "判断题"}, {"id": 467, "type": "判断题", "question": "在函数中，传入列表、字典等可变对象属于引用传递", "options": ["对", "错"], "answer": "A", "analysis": "", "sheet": "判断题"}, {"id": 468, "type": "判断题", "question": "SAN是聚类算法", "options": ["对", "错"], "answer": "A", "analysis": "", "sheet": "判断题"}, {"id": 469, "type": "判断题", "question": "主构造器在每个类都可以定义多个", "options": ["对", "错"], "answer": "B", "analysis": "", "sheet": "判断题"}, {"id": 470, "type": "判断题", "question": "Jobtracke通常与NameNode 在同一个节点启动", "options": ["对", "错"], "answer": "A", "analysis": "", "sheet": "判断题"}, {"id": 471, "type": "判断题", "question": "带有else子句的循环如果因为执行了break语句而退出的话，则会执行else子句中的代码。", "options": ["对", "错"], "answer": "B", "analysis": "", "sheet": "判断题"}, {"id": 472, "type": "判断题", "question": "from scipy import misc \nface = misc.face()\nflip_ud_face = np.flipud(face)读入图像并翻转", "options": ["对", "错"], "answer": "A", "analysis": "", "sheet": "判断题"}, {"id": 473, "type": "判断题", "question": "马赫带效应是指图像不同灰度级条带之间在灰度交界处存在的毛边现象", "options": ["对", "错"], "answer": "A", "analysis": "", "sheet": "判断题"}, {"id": 474, "type": "判断题", "question": "只有Python扩展库才需要导入以后才能使用其中的对象，Python标准库不需要导入即可使用其中的所有对象和方法。", "options": ["对", "错"], "answer": "B", "analysis": "", "sheet": "判断题"}, {"id": 475, "type": "判断题", "question": "在try...except...else结构中，如果try块的语句引发了异常则会执行else块中的代码。", "options": ["对", "错"], "answer": "B", "analysis": "", "sheet": "判断题"}, {"id": 476, "type": "判断题", "question": "继承自threading.Thread类的派生类中不能有普通的成员方法。", "options": ["对", "错"], "answer": "B", "analysis": "", "sheet": "判断题"}, {"id": 477, "type": "判断题", "question": "异常处理结构也不是万能的，处理异常的代码也有引发异常的可能。", "options": ["对", "错"], "answer": "A", "analysis": "", "sheet": "判断题"}, {"id": 478, "type": "判断题", "question": "在编写函数时，建议首先对形参进行类型检查和数值范围检查之后再编写功能代码，或者使用异常处理结构，尽量避免代码抛出异常而导致程序崩溃。", "options": ["对", "错"], "answer": "A", "analysis": "", "sheet": "判断题"}, {"id": 479, "type": "判断题", "question": "查看数据的维度大小：data.shape", "options": ["对", "错"], "answer": "A", "analysis": "", "sheet": "判断题"}, {"id": 480, "type": "判断题", "question": "Python采用的是基于值得自动内存管理方式。", "options": ["对", "错"], "answer": "A", "analysis": "", "sheet": "判断题"}, {"id": 481, "type": "判断题", "question": "数组a按行的最大值：np.max(a, axis = 1)", "options": ["对", "错"], "answer": "A", "analysis": "", "sheet": "判断题"}, {"id": 482, "type": "判断题", "question": "Hadoop 可以运行单机（本地）模式", "options": ["对", "错"], "answer": "A", "analysis": "", "sheet": "判断题"}, {"id": 483, "type": "判断题", "question": "Nagios 不可以监控 Hadoop 集群，因为它不提供 Hadoop 支持。", "options": ["对", "错"], "answer": "B", "analysis": "", "sheet": "判断题"}, {"id": 484, "type": "判断题", "question": "使用列表对象的remove()方法可以删除列表中首次出现的指定元素，如果列中不存在要删除的指定元素则抛出异常。", "options": ["对", "错"], "answer": "A", "analysis": "", "sheet": "判断题"}, {"id": 485, "type": "判断题", "question": "NameNode 本地磁盘保存了 Block 的位置信息", "options": ["对", "错"], "answer": "B", "analysis": "", "sheet": "判断题"}, {"id": 486, "type": "判断题", "question": "stage如果失败会自动进行特定次数的重试，而且只会计算失败的分片", "options": ["对", "错"], "answer": "A", "analysis": "", "sheet": "判断题"}, {"id": 487, "type": "判断题", "question": "损失函数可以用于评价模型的拟合效果", "options": ["对", "错"], "answer": "A", "analysis": "", "sheet": "判断题"}, {"id": 488, "type": "判断题", "question": "HBase依靠HDFS存储底层数据。", "options": ["对", "错"], "answer": "A", "analysis": "", "sheet": "判断题"}, {"id": 489, "type": "判断题", "question": "Hadoop 自身具有严格的权限管理和安全措施保障集群正常运行。", "options": ["对", "错"], "answer": "B", "analysis": "", "sheet": "判断题"}, {"id": 490, "type": "判断题", "question": "stats.kurtosistest()计算数据分布的偏度", "options": ["对", "错"], "answer": "B", "analysis": "", "sheet": "判断题"}, {"id": 491, "type": "判断题", "question": "运行在集群上的用户程序，包含集群上的driver program 和多个executor线程组成", "options": ["对", "错"], "answer": "A", "analysis": "", "sheet": "判断题"}, {"id": 492, "type": "判断题", "question": "创建一个长度为10的零向量，并把第五个值赋值为1：Z = np.zeros(10);Z[4] = 1", "options": ["对", "错"], "answer": "A", "analysis": "", "sheet": "判断题"}, {"id": 493, "type": "判断题", "question": "Z = np.arange(10) 筛选出数组中5到8的索引的位置：Z[5:8]", "options": ["对", "错"], "answer": "A", "analysis": "", "sheet": "判断题"}, {"id": 494, "type": "判断题", "question": "对RDD每个元素转换，文件中的每一行数据返回多个数组对象", "options": ["对", "错"], "answer": "B", "analysis": "", "sheet": "判断题"}, {"id": 495, "type": "判断题", "question": "构造一个数组，让它不能被改变：\nz=np.zeros(5)\nz.flags.writeable=False", "options": ["对", "错"], "answer": "A", "analysis": "", "sheet": "判断题"}, {"id": 496, "type": "判断题", "question": "若添加了一个不重要的特征，可能增加了模型的复杂度", "options": ["对", "错"], "answer": "A", "analysis": "", "sheet": "判断题"}, {"id": 497, "type": "判断题", "question": "集群的最主要瓶颈是磁盘IO", "options": ["对", "错"], "answer": "A", "analysis": "", "sheet": "判断题"}]